{
  "meta": {
    "generated": "2026-07-05 20:40:33 UTC"
  },
  "totals": {
    "wagered": 0.0,
    "open_stake": 0.0,
    "settled_pl": 0.0,
    "n_bets": 0
  },
  "totals_by_currency": {
    "GBP": {
      "wagered": 0.0,
      "open_stake": 0.0,
      "settled_pl": 0.0,
      "n_bets": 0
    },
    "USD": {
      "wagered": 0.0,
      "open_stake": 1317.9064,
      "settled_pl": 0.0,
      "n_bets": 11
    }
  },
  "venues": {
    "sportsbook": {
      "wagered": 0.0,
      "open_stake": 0.0,
      "settled_pl": 0.0,
      "n_bets": 0,
      "currency": "GBP"
    },
    "polymarket": {
      "wagered": 0.0,
      "open_stake": 1317.9064,
      "settled_pl": 0.0,
      "n_bets": 11,
      "currency": "USD"
    },
    "kalshi": {
      "wagered": 0.0,
      "open_stake": 0.0,
      "settled_pl": 0.0,
      "n_bets": 0,
      "currency": "USD"
    },
    "sportsbook_1": {
      "wagered": 0.0,
      "open_stake": 0.0,
      "settled_pl": 0.0,
      "n_bets": 0,
      "currency": "GBP",
      "label": "Sportsbook 1"
    },
    "sportsbook_2": {
      "wagered": 0.0,
      "open_stake": 0.0,
      "settled_pl": 0.0,
      "n_bets": 0,
      "currency": "GBP",
      "label": "Sportsbook 2"
    }
  },
  "source_summary": {},
  "platforms": {},
  "platforms_by_account": {},
  "closed_positions": [],
  "pnl_series": {
    "sportsbook": {
      "currency": "GBP",
      "points": []
    },
    "prediction_markets": {
      "currency": "USD",
      "points": []
    }
  },
  "clv": {
    "avg_clv": null,
    "pct_beat_close": null,
    "n_with_close": 0
  },
  "positions": [
    {
      "id": "pm-0x8bdf55664c",
      "ts_utc": "",
      "match": "Will Spain reach the 2026 FIFA World Cup final?",
      "match_id": "0x8bdf55664cb17a543fef1f43bd6aeb0aa7b7849cb31620808ce258b3e2ab136d",
      "market": "Will Spain reach the 2026 FIFA World Cup final?",
      "selection": "Yes",
      "platform": "polymarket",
      "venue": "polymarket",
      "account": "1",
      "source": "manual",
      "currency": "USD",
      "decimal_odds": 4.168403501458942,
      "stake": 199.9991,
      "model_prob": null,
      "market_prob_devig": null,
      "ev": null,
      "kelly_fraction": null,
      "cur_value": 204.17,
      "cur_price": 0.245,
      "avg_price": 0.2399,
      "shares": 833.3333,
      "cash_pnl": 4.17,
      "pct_pnl": 0.020850093825422213,
      "notes": "live PM position (data-API)"
    },
    {
      "id": "pm-0x508af22a38",
      "ts_utc": "",
      "match": "Will France reach the Semifinals at the 2026 FIFA World Cup?",
      "match_id": "0x508af22a38ad600b6b7526970e26be280e4183731954b575320050735d991fa8",
      "market": "Will France reach the Semifinals at the 2026 FIFA World Cup?",
      "selection": "Yes",
      "platform": "polymarket",
      "venue": "polymarket",
      "account": "1",
      "source": "manual",
      "currency": "USD",
      "decimal_odds": 1.9474196689386565,
      "stake": 214.9996,
      "model_prob": null,
      "market_prob_devig": null,
      "ev": null,
      "kelly_fraction": null,
      "cur_value": 328.61,
      "cur_price": 0.785,
      "avg_price": 0.5135,
      "shares": 418.6153,
      "cash_pnl": 113.61,
      "pct_pnl": 0.5284195877573726,
      "notes": "live PM position (data-API)"
    },
    {
      "id": "pm-0xa6ea855bd1",
      "ts_utc": "",
      "match": "Will Brazil reach the Quarterfinals at the 2026 FIFA World Cup?",
      "match_id": "0xa6ea855bd19f78e136d6d2ebf8ca20dbeabcd123b464cbda065a0d6cf35c200f",
      "market": "Will Brazil reach the Quarterfinals at the 2026 FIFA World Cup?",
      "selection": "Yes",
      "platform": "polymarket",
      "venue": "polymarket",
      "account": "1",
      "source": "manual",
      "currency": "USD",
      "decimal_odds": 1.985308715505261,
      "stake": 169.9992,
      "model_prob": null,
      "market_prob_devig": null,
      "ev": null,
      "kelly_fraction": null,
      "cur_value": 226.08,
      "cur_price": 0.67,
      "avg_price": 0.5037,
      "shares": 337.4399,
      "cash_pnl": 56.09,
      "pct_pnl": 0.3299427291422548,
      "notes": "live PM position (data-API)"
    },
    {
      "id": "pm-0x66dfece624",
      "ts_utc": "",
      "match": "Will Belgium reach the Quarterfinals at the 2026 FIFA World Cup?",
      "match_id": "0x66dfece624b1a37854515001d5514ee2263fb5ae4c8120ec264d47c677a22c1a",
      "market": "Will Belgium reach the Quarterfinals at the 2026 FIFA World Cup?",
      "selection": "Yes",
      "platform": "polymarket",
      "venue": "polymarket",
      "account": "1",
      "source": "manual",
      "currency": "USD",
      "decimal_odds": 1.9833399444664817,
      "stake": 161.3797,
      "model_prob": null,
      "market_prob_devig": null,
      "ev": null,
      "kelly_fraction": null,
      "cur_value": 153.47,
      "cur_price": 0.4795,
      "avg_price": 0.5042,
      "shares": 320.0689,
      "cash_pnl": -7.91,
      "pct_pnl": -0.04901483891716244,
      "notes": "live PM position (data-API)"
    },
    {
      "id": "pm-0x4da81003b8",
      "ts_utc": "",
      "match": "Will England reach the Quarterfinals at the 2026 FIFA World Cup?",
      "match_id": "0x4da81003b84738e6edd6b2c378ca06960df9907f978a8f8fe91d37de6aa2e594",
      "market": "Will England reach the Quarterfinals at the 2026 FIFA World Cup?",
      "selection": "Yes",
      "platform": "polymarket",
      "venue": "polymarket",
      "account": "1",
      "source": "manual",
      "currency": "USD",
      "decimal_odds": 1.8518518518518516,
      "stake": 161.3799,
      "model_prob": null,
      "market_prob_devig": null,
      "ev": null,
      "kelly_fraction": null,
      "cur_value": 156.9,
      "cur_price": 0.525,
      "avg_price": 0.54,
      "shares": 298.8518,
      "cash_pnl": -4.48,
      "pct_pnl": -0.027760582327786797,
      "notes": "live PM position (data-API)"
    },
    {
      "id": "pm-0x2a0e8ce7c3",
      "ts_utc": "",
      "match": "Will Brazil win on 2026-07-05?",
      "match_id": "0x2a0e8ce7c309ec8015c4c721dec574ff100b0512ef412a54bb733dc5bef740dc",
      "market": "Will Brazil win on 2026-07-05?",
      "selection": "Yes",
      "platform": "polymarket",
      "venue": "polymarket",
      "account": "1",
      "source": "manual",
      "currency": "USD",
      "decimal_odds": 1.8800526414739611,
      "stake": 132.2896,
      "model_prob": null,
      "market_prob_devig": null,
      "ev": null,
      "kelly_fraction": null,
      "cur_value": 130.57,
      "cur_price": 0.525,
      "avg_price": 0.5319,
      "shares": 248.7058,
      "cash_pnl": -1.72,
      "pct_pnl": -0.01300177791753849,
      "notes": "live PM position (data-API)"
    },
    {
      "id": "pm-0x02103f049a",
      "ts_utc": "",
      "match": "Will Belgium win on 2026-07-06?",
      "match_id": "0x02103f049a5fe127c4ea03c9531772e82f3b9f5e9f5f30d67fda5b472fb56c17",
      "market": "Will Belgium win on 2026-07-06?",
      "selection": "Yes",
      "platform": "polymarket",
      "venue": "polymarket",
      "account": "1",
      "source": "manual",
      "currency": "USD",
      "decimal_odds": 2.632271650434325,
      "stake": 66.9998,
      "model_prob": null,
      "market_prob_devig": null,
      "ev": null,
      "kelly_fraction": null,
      "cur_value": 64.36,
      "cur_price": 0.365,
      "avg_price": 0.3799,
      "shares": 176.3157,
      "cash_pnl": -2.64,
      "pct_pnl": -0.039403102695828945,
      "notes": "live PM position (data-API)"
    },
    {
      "id": "pm-0x99f0c39e42",
      "ts_utc": "",
      "match": "Will England win on 2026-07-05?",
      "match_id": "0x99f0c39e4235d840bd25d2c229b2cda57cc087b6b8c2780f804fffeed0d0c628",
      "market": "Will England win on 2026-07-05?",
      "selection": "Yes",
      "platform": "polymarket",
      "venue": "polymarket",
      "account": "1",
      "source": "manual",
      "currency": "USD",
      "decimal_odds": 2.4813895781637716,
      "stake": 67.8598,
      "model_prob": null,
      "market_prob_devig": null,
      "ev": null,
      "kelly_fraction": null,
      "cur_value": 63.14,
      "cur_price": 0.375,
      "avg_price": 0.403,
      "shares": 168.378,
      "cash_pnl": -4.72,
      "pct_pnl": -0.06955517110277365,
      "notes": "live PM position (data-API)"
    },
    {
      "id": "pm-0x14dc2b2815",
      "ts_utc": "",
      "match": "Will Portugal reach the Quarterfinals at the 2026 FIFA World Cup?",
      "match_id": "0x14dc2b28157393f32a3a9a1827024b258156eefd4be567b8f3dc97d437e98af2",
      "market": "Will Portugal reach the Quarterfinals at the 2026 FIFA World Cup?",
      "selection": "Yes",
      "platform": "polymarket",
      "venue": "polymarket",
      "account": "1",
      "source": "manual",
      "currency": "USD",
      "decimal_odds": 1.9234468166955183,
      "stake": 66.9998,
      "model_prob": null,
      "market_prob_devig": null,
      "ev": null,
      "kelly_fraction": null,
      "cur_value": 43.16,
      "cur_price": 0.335,
      "avg_price": 0.5199,
      "shares": 128.8461,
      "cash_pnl": -23.84,
      "pct_pnl": -0.35582195767748565,
      "notes": "live PM position (data-API)"
    },
    {
      "id": "pm-0x5ddf2373c4",
      "ts_utc": "",
      "match": "Will Argentina reach the Quarterfinals at the 2026 FIFA World Cup?",
      "match_id": "0x5ddf2373c4c9d01a305666b767d768c7e85fc329df2fd6f489ea57318c8f9a20",
      "market": "Will Argentina reach the Quarterfinals at the 2026 FIFA World Cup?",
      "selection": "Yes",
      "platform": "polymarket",
      "venue": "polymarket",
      "account": "1",
      "source": "manual",
      "currency": "USD",
      "decimal_odds": 1.25,
      "stake": 70.0,
      "model_prob": null,
      "market_prob_devig": null,
      "ev": null,
      "kelly_fraction": null,
      "cur_value": 74.81,
      "cur_price": 0.855,
      "avg_price": 0.8,
      "shares": 87.5,
      "cash_pnl": 4.81,
      "pct_pnl": 0.06871428571428571,
      "notes": "live PM position (data-API)"
    },
    {
      "id": "pm-0x375409bc5e",
      "ts_utc": "",
      "match": "Will England win the 2026 FIFA World Cup?",
      "match_id": "0x375409bc5eeeff961e82b479caeccc20f33d15738e5bce1186d628aa3d9dfb1f",
      "market": "Will England win the 2026 FIFA World Cup?",
      "selection": "No",
      "platform": "polymarket",
      "venue": "polymarket",
      "account": "1",
      "source": "manual",
      "currency": "USD",
      "decimal_odds": 1.1469205184080744,
      "stake": 5.9999,
      "model_prob": null,
      "market_prob_devig": null,
      "ev": null,
      "kelly_fraction": null,
      "cur_value": 6.37,
      "cur_price": 0.9255,
      "avg_price": 0.8719,
      "shares": 6.8807,
      "cash_pnl": 0.37,
      "pct_pnl": 0.06166769446157436,
      "notes": "live PM position (data-API)"
    }
  ],
  "dropped_open_bets": [],
  "predictions": [
    {
      "fixture": "Mexico vs England",
      "scores": [
        {
          "score": "1-1",
          "prob": 13.7,
          "fair": 7.3,
          "back": 7.44
        },
        {
          "score": "2-1",
          "prob": 7.9,
          "fair": 12.64,
          "back": 12.89
        },
        {
          "score": "0-1",
          "prob": 7.8,
          "fair": 12.75,
          "back": 13.0
        },
        {
          "score": "1-2",
          "prob": 7.8,
          "fair": 12.82,
          "back": 13.08
        },
        {
          "score": "1-0",
          "prob": 7.7,
          "fair": 12.96,
          "back": 13.22
        },
        {
          "score": "0-0",
          "prob": 7.6,
          "fair": 13.13,
          "back": 13.39
        }
      ],
      "over_under": {
        "line": 2.5,
        "over": 51.4,
        "under": 48.6
      },
      "btts": 56.4,
      "xg_home": 1.23,
      "xg_away": 1.52
    },
    {
      "fixture": "United States vs Belgium",
      "scores": [
        {
          "score": "1-1",
          "prob": 11.8,
          "fair": 8.51,
          "back": 8.68
        },
        {
          "score": "2-1",
          "prob": 8.2,
          "fair": 12.24,
          "back": 12.49
        },
        {
          "score": "2-2",
          "prob": 7.6,
          "fair": 13.09,
          "back": 13.35
        },
        {
          "score": "1-2",
          "prob": 7.5,
          "fair": 13.33,
          "back": 13.59
        },
        {
          "score": "1-0",
          "prob": 5.4,
          "fair": 18.56,
          "back": 18.93
        },
        {
          "score": "0-2",
          "prob": 5.4,
          "fair": 18.65,
          "back": 19.03
        }
      ],
      "over_under": {
        "line": 2.5,
        "over": 63.5,
        "under": 36.5
      },
      "btts": 66.3,
      "xg_home": 1.52,
      "xg_away": 1.78
    },
    {
      "fixture": "Portugal vs Spain",
      "scores": [
        {
          "score": "1-1",
          "prob": 12.6,
          "fair": 7.94,
          "back": 8.09
        },
        {
          "score": "0-1",
          "prob": 10.6,
          "fair": 9.42,
          "back": 9.6
        },
        {
          "score": "1-2",
          "prob": 9.9,
          "fair": 10.11,
          "back": 10.31
        },
        {
          "score": "0-2",
          "prob": 8.7,
          "fair": 11.52,
          "back": 11.75
        },
        {
          "score": "0-0",
          "prob": 7.4,
          "fair": 13.44,
          "back": 13.71
        },
        {
          "score": "1-0",
          "prob": 6.4,
          "fair": 15.58,
          "back": 15.89
        }
      ],
      "over_under": {
        "line": 2.5,
        "over": 50.3,
        "under": 49.7
      },
      "btts": 53.9,
      "xg_home": 1.09,
      "xg_away": 1.59
    },
    {
      "fixture": "Argentina vs Egypt",
      "scores": [
        {
          "score": "2-0",
          "prob": 14.5,
          "fair": 6.9,
          "back": 7.04
        },
        {
          "score": "1-0",
          "prob": 14.1,
          "fair": 7.11,
          "back": 7.25
        },
        {
          "score": "3-0",
          "prob": 9.6,
          "fair": 10.4,
          "back": 10.6
        },
        {
          "score": "2-1",
          "prob": 9.6,
          "fair": 10.43,
          "back": 10.64
        },
        {
          "score": "1-1",
          "prob": 9.2,
          "fair": 10.85,
          "back": 11.06
        },
        {
          "score": "0-0",
          "prob": 7.1,
          "fair": 14.06,
          "back": 14.34
        }
      ],
      "over_under": {
        "line": 2.5,
        "over": 50.1,
        "under": 49.9
      },
      "btts": 41.8,
      "xg_home": 2.04,
      "xg_away": 0.64
    },
    {
      "fixture": "Switzerland vs Colombia",
      "scores": [
        {
          "score": "1-1",
          "prob": 14.3,
          "fair": 7.02,
          "back": 7.16
        },
        {
          "score": "0-1",
          "prob": 10.5,
          "fair": 9.52,
          "back": 9.71
        },
        {
          "score": "0-0",
          "prob": 9.5,
          "fair": 10.58,
          "back": 10.79
        },
        {
          "score": "1-2",
          "prob": 8.6,
          "fair": 11.65,
          "back": 11.88
        },
        {
          "score": "0-2",
          "prob": 8.1,
          "fair": 12.33,
          "back": 12.58
        },
        {
          "score": "1-0",
          "prob": 7.9,
          "fair": 12.63,
          "back": 12.88
        }
      ],
      "over_under": {
        "line": 2.5,
        "over": 45.2,
        "under": 54.8
      },
      "btts": 51.4,
      "xg_home": 1.07,
      "xg_away": 1.43
    },
    {
      "fixture": "France vs Morocco",
      "scores": [
        {
          "score": "1-0",
          "prob": 17.1,
          "fair": 5.86,
          "back": 5.98
        },
        {
          "score": "2-0",
          "prob": 12.5,
          "fair": 8.01,
          "back": 8.17
        },
        {
          "score": "1-1",
          "prob": 11.6,
          "fair": 8.6,
          "back": 8.77
        },
        {
          "score": "0-0",
          "prob": 10.6,
          "fair": 9.47,
          "back": 9.66
        },
        {
          "score": "2-1",
          "prob": 9.8,
          "fair": 10.16,
          "back": 10.36
        },
        {
          "score": "0-1",
          "prob": 6.6,
          "fair": 15.08,
          "back": 15.39
        }
      ],
      "over_under": {
        "line": 2.5,
        "over": 38.8,
        "under": 61.2
      },
      "btts": 40.9,
      "xg_home": 1.51,
      "xg_away": 0.72
    }
  ]
}
