{
  "meta": {
    "generated": "2026-07-07 05:15:25 UTC"
  },
  "fixtures": [
    {
      "fixture": "Argentina vs Egypt",
      "scores": [
        {
          "score": "2-0",
          "prob": 14.7,
          "fair": 6.8,
          "pm_prob": 16.5
        },
        {
          "score": "1-0",
          "prob": 14.2,
          "fair": 7.03,
          "pm_prob": 15.5
        },
        {
          "score": "3-0",
          "prob": 9.8,
          "fair": 10.25,
          "pm_prob": 10.5
        },
        {
          "score": "2-1",
          "prob": 9.7,
          "fair": 10.32,
          "pm_prob": 9.5
        },
        {
          "score": "1-1",
          "prob": 9.0,
          "fair": 11.07,
          "pm_prob": 9.5
        },
        {
          "score": "0-0",
          "prob": 7.0,
          "fair": 14.29,
          "pm_prob": 6.5
        }
      ],
      "over_under": {
        "line": 2.5,
        "over": 50.3,
        "under": 49.7
      },
      "btts": 41.6,
      "model_1x2": {
        "home": 0.716901,
        "draw": 0.192852,
        "away": 0.090247
      },
      "approx_1x2": false,
      "venues": [
        {
          "venue": "polymarket",
          "selection_prices": {
            "home": 1.3793,
            "draw": 5.1282,
            "away": 11.7647
          },
          "implied": {
            "home": 0.7250054375407816,
            "draw": 0.19500019500019503,
            "away": 0.08500004250002126
          },
          "edge_vs_model": {
            "home": -0.011178450700000009,
            "draw": -0.011016373600000073,
            "away": 0.06172888089999984
          }
        }
      ],
      "kickoff": "2026-07-07T16:00:00+00:00"
    },
    {
      "fixture": "Switzerland vs Colombia",
      "scores": [
        {
          "score": "1-1",
          "prob": 14.3,
          "fair": 7.0,
          "pm_prob": 14.5
        },
        {
          "score": "0-1",
          "prob": 10.5,
          "fair": 9.49,
          "pm_prob": 12.5
        },
        {
          "score": "0-0",
          "prob": 9.6,
          "fair": 10.44,
          "pm_prob": 10.5
        },
        {
          "score": "1-2",
          "prob": 8.6,
          "fair": 11.64,
          "pm_prob": 9.5
        },
        {
          "score": "0-2",
          "prob": 8.1,
          "fair": 12.31,
          "pm_prob": 8.5
        },
        {
          "score": "1-0",
          "prob": 7.9,
          "fair": 12.62,
          "pm_prob": 9.5
        }
      ],
      "over_under": {
        "line": 2.5,
        "over": 45.0,
        "under": 55.0
      },
      "btts": 51.2,
      "model_1x2": {
        "home": 0.268951,
        "draw": 0.300206,
        "away": 0.430843
      },
      "approx_1x2": false,
      "venues": [
        {
          "venue": "polymarket",
          "selection_prices": {
            "home": 3.7736,
            "draw": 3.1746,
            "away": 2.3529
          },
          "implied": {
            "home": 0.26499894000423996,
            "draw": 0.315000315000315,
            "away": 0.4250074376301585
          },
          "edge_vs_model": {
            "home": 0.014913493599999939,
            "draw": -0.04696603240000008,
            "away": 0.013730494699999873
          }
        }
      ],
      "kickoff": "2026-07-07T20:00:00+00:00"
    },
    {
      "fixture": "France vs Morocco",
      "scores": [
        {
          "score": "1-0",
          "prob": 17.0,
          "fair": 5.87,
          "pm_prob": 13.5
        },
        {
          "score": "2-0",
          "prob": 12.5,
          "fair": 7.99,
          "pm_prob": 12.5
        },
        {
          "score": "1-1",
          "prob": 11.6,
          "fair": 8.59,
          "pm_prob": 11.5
        },
        {
          "score": "0-0",
          "prob": 10.6,
          "fair": 9.43,
          "pm_prob": 7.5
        },
        {
          "score": "2-1",
          "prob": 9.8,
          "fair": 10.17,
          "pm_prob": 10.5
        },
        {
          "score": "0-1",
          "prob": 6.6,
          "fair": 15.17,
          "pm_prob": 5.5
        }
      ],
      "over_under": {
        "line": 2.5,
        "over": 38.8,
        "under": 61.2
      },
      "btts": 40.9,
      "model_1x2": {
        "home": 0.577905,
        "draw": 0.256917,
        "away": 0.165178
      },
      "approx_1x2": false,
      "venues": [
        {
          "venue": "polymarket",
          "selection_prices": {
            "home": 1.626,
            "draw": 4.0816,
            "away": 6.8966
          },
          "implied": {
            "home": 0.6150061500615006,
            "draw": 0.24500196001568014,
            "away": 0.14499898500710495
          },
          "edge_vs_model": {
            "home": -0.06032647000000002,
            "draw": 0.04863242720000005,
            "away": 0.13916659480000004
          }
        }
      ],
      "kickoff": "2026-07-09T20:00:00+00:00"
    }
  ]
}
