{
  "meta": {
    "generated": "2026-07-11 02:52:29 UTC"
  },
  "fixtures": [
    {
      "fixture": "Norway vs England",
      "scores": [
        {
          "score": "1-1",
          "prob": 12.1,
          "fair": 8.26
        },
        {
          "score": "0-1",
          "prob": 10.3,
          "fair": 9.71
        },
        {
          "score": "0-2",
          "prob": 9.7,
          "fair": 10.31
        },
        {
          "score": "1-2",
          "prob": 8.6,
          "fair": 11.63
        },
        {
          "score": "0-0",
          "prob": 7.8,
          "fair": 12.82
        },
        {
          "score": "1-0",
          "prob": 7.2,
          "fair": 13.89
        }
      ],
      "over_under": {
        "line": 2.5,
        "over": 49.3,
        "under": 50.7
      },
      "btts": 50.4,
      "model_1x2": {
        "home": 0.230435,
        "draw": 0.254962,
        "away": 0.514603
      },
      "approx_1x2": false,
      "venues": [
        {
          "venue": "virginbet",
          "selection_prices": {
            "home": 3.95,
            "draw": 3.55,
            "away": 1.86
          },
          "implied": {
            "home": 0.2531645569620253,
            "draw": 0.28169014084507044,
            "away": 0.5376344086021505
          },
          "edge_vs_model": {
            "home": -0.08978175,
            "draw": -0.09488489999999994,
            "away": -0.04283841999999993
          }
        },
        {
          "venue": "coral",
          "selection_prices": {
            "home": 3.75,
            "draw": 3.6,
            "away": 1.95
          },
          "implied": {
            "home": 0.26666666666666666,
            "draw": 0.2777777777777778,
            "away": 0.5128205128205129
          },
          "edge_vs_model": {
            "home": -0.13586874999999998,
            "draw": -0.0821367999999999,
            "away": 0.003475850000000058
          }
        },
        {
          "venue": "grosvenor",
          "selection_prices": {
            "home": 4.0,
            "draw": 3.5,
            "away": 1.91
          },
          "implied": {
            "home": 0.25,
            "draw": 0.2857142857142857,
            "away": 0.5235602094240838
          },
          "edge_vs_model": {
            "home": -0.07826,
            "draw": -0.10763299999999987,
            "away": -0.017108269999999925
          }
        },
        {
          "venue": "ladbrokes_uk",
          "selection_prices": {
            "home": 3.7,
            "draw": 3.6,
            "away": 1.95
          },
          "implied": {
            "home": 0.27027027027027023,
            "draw": 0.2777777777777778,
            "away": 0.5128205128205129
          },
          "edge_vs_model": {
            "home": -0.14739049999999998,
            "draw": -0.0821367999999999,
            "away": 0.003475850000000058
          }
        },
        {
          "venue": "smarkets",
          "selection_prices": {
            "home": 4.2,
            "draw": 3.85,
            "away": 1.96
          },
          "implied": {
            "home": 0.23809523809523808,
            "draw": 0.2597402597402597,
            "away": 0.5102040816326531
          },
          "edge_vs_model": {
            "home": -0.03217300000000001,
            "draw": -0.01839629999999992,
            "away": 0.00862187999999997
          }
        },
        {
          "venue": "casumo",
          "selection_prices": {
            "home": 4.1,
            "draw": 3.6,
            "away": 1.88
          },
          "implied": {
            "home": 0.24390243902439027,
            "draw": 0.2777777777777778,
            "away": 0.5319148936170213
          },
          "edge_vs_model": {
            "home": -0.05521650000000011,
            "draw": -0.0821367999999999,
            "away": -0.032546359999999996
          }
        },
        {
          "venue": "livescorebet",
          "selection_prices": {
            "home": 3.95,
            "draw": 3.55,
            "away": 1.86
          },
          "implied": {
            "home": 0.2531645569620253,
            "draw": 0.28169014084507044,
            "away": 0.5376344086021505
          },
          "edge_vs_model": {
            "home": -0.08978175,
            "draw": -0.09488489999999994,
            "away": -0.04283841999999993
          }
        },
        {
          "venue": "betway",
          "selection_prices": {
            "home": 3.8,
            "draw": 3.6,
            "away": 1.88
          },
          "implied": {
            "home": 0.2631578947368421,
            "draw": 0.2777777777777778,
            "away": 0.5319148936170213
          },
          "edge_vs_model": {
            "home": -0.12434699999999999,
            "draw": -0.0821367999999999,
            "away": -0.032546359999999996
          }
        },
        {
          "venue": "betfred_uk",
          "selection_prices": {
            "home": 4.0,
            "draw": 3.6,
            "away": 1.9
          },
          "implied": {
            "home": 0.25,
            "draw": 0.2777777777777778,
            "away": 0.5263157894736842
          },
          "edge_vs_model": {
            "home": -0.07826,
            "draw": -0.0821367999999999,
            "away": -0.02225429999999995
          }
        },
        {
          "venue": "unibet_uk",
          "selection_prices": {
            "home": 4.2,
            "draw": 3.75,
            "away": 1.91
          },
          "implied": {
            "home": 0.23809523809523808,
            "draw": 0.26666666666666666,
            "away": 0.5235602094240838
          },
          "edge_vs_model": {
            "home": -0.03217300000000001,
            "draw": -0.04389249999999989,
            "away": -0.017108269999999925
          }
        },
        {
          "venue": "leovegas",
          "selection_prices": {
            "home": 4.0,
            "draw": 3.6,
            "away": 1.9
          },
          "implied": {
            "home": 0.25,
            "draw": 0.2777777777777778,
            "away": 0.5263157894736842
          },
          "edge_vs_model": {
            "home": -0.07826,
            "draw": -0.0821367999999999,
            "away": -0.02225429999999995
          }
        },
        {
          "venue": "paddypower",
          "selection_prices": {
            "home": 3.8,
            "draw": 3.6,
            "away": 1.87
          },
          "implied": {
            "home": 0.2631578947368421,
            "draw": 0.2777777777777778,
            "away": 0.53475935828877
          },
          "edge_vs_model": {
            "home": -0.12434699999999999,
            "draw": -0.0821367999999999,
            "away": -0.03769238999999991
          }
        },
        {
          "venue": "skybet",
          "selection_prices": {
            "home": 3.8,
            "draw": 3.75,
            "away": 1.85
          },
          "implied": {
            "home": 0.2631578947368421,
            "draw": 0.26666666666666666,
            "away": 0.5405405405405405
          },
          "edge_vs_model": {
            "home": -0.12434699999999999,
            "draw": -0.04389249999999989,
            "away": -0.047984449999999845
          }
        },
        {
          "venue": "betvictor",
          "selection_prices": {
            "home": 3.8,
            "draw": 3.7,
            "away": 1.87
          },
          "implied": {
            "home": 0.2631578947368421,
            "draw": 0.27027027027027023,
            "away": 0.53475935828877
          },
          "edge_vs_model": {
            "home": -0.12434699999999999,
            "draw": -0.05664059999999982,
            "away": -0.03769238999999991
          }
        },
        {
          "venue": "betfair_ex_uk",
          "selection_prices": {
            "home": 4.2,
            "draw": 3.85,
            "away": 1.97
          },
          "implied": {
            "home": 0.23809523809523808,
            "draw": 0.2597402597402597,
            "away": 0.5076142131979695
          },
          "edge_vs_model": {
            "home": -0.03217300000000001,
            "draw": -0.01839629999999992,
            "away": 0.013767910000000105
          }
        },
        {
          "venue": "matchbook",
          "selection_prices": {
            "home": 4.2,
            "draw": 3.8,
            "away": 1.97
          },
          "implied": {
            "home": 0.23809523809523808,
            "draw": 0.2631578947368421,
            "away": 0.5076142131979695
          },
          "edge_vs_model": {
            "home": -0.03217300000000001,
            "draw": -0.03114439999999996,
            "away": 0.013767910000000105
          }
        },
        {
          "venue": "sport888",
          "selection_prices": {
            "home": 3.8,
            "draw": 3.4,
            "away": 1.85
          },
          "implied": {
            "home": 0.2631578947368421,
            "draw": 0.29411764705882354,
            "away": 0.5405405405405405
          },
          "edge_vs_model": {
            "home": -0.12434699999999999,
            "draw": -0.13312919999999995,
            "away": -0.047984449999999845
          }
        },
        {
          "venue": "williamhill",
          "selection_prices": {
            "home": 3.9,
            "draw": 3.5,
            "away": 1.85
          },
          "implied": {
            "home": 0.25641025641025644,
            "draw": 0.2857142857142857,
            "away": 0.5405405405405405
          },
          "edge_vs_model": {
            "home": -0.10130349999999999,
            "draw": -0.10763299999999987,
            "away": -0.047984449999999845
          }
        },
        {
          "venue": "boylesports",
          "selection_prices": {
            "home": 4.0,
            "draw": 3.6,
            "away": 1.83
          },
          "implied": {
            "home": 0.25,
            "draw": 0.2777777777777778,
            "away": 0.5464480874316939
          },
          "edge_vs_model": {
            "home": -0.07826,
            "draw": -0.0821367999999999,
            "away": -0.05827650999999989
          }
        },
        {
          "venue": "betfair_sb_uk",
          "selection_prices": {
            "home": 4.0,
            "draw": 3.7,
            "away": 1.91
          },
          "implied": {
            "home": 0.25,
            "draw": 0.27027027027027023,
            "away": 0.5235602094240838
          },
          "edge_vs_model": {
            "home": -0.07826,
            "draw": -0.05664059999999982,
            "away": -0.017108269999999925
          }
        }
      ],
      "kickoff": "2026-07-11T21:00:00+00:00"
    },
    {
      "fixture": "Argentina vs Switzerland",
      "scores": [
        {
          "score": "1-1",
          "prob": 12.4,
          "fair": 8.06
        },
        {
          "score": "1-0",
          "prob": 11.2,
          "fair": 8.93
        },
        {
          "score": "2-0",
          "prob": 10.6,
          "fair": 9.43
        },
        {
          "score": "2-1",
          "prob": 9.9,
          "fair": 10.1
        },
        {
          "score": "0-0",
          "prob": 7.6,
          "fair": 13.16
        },
        {
          "score": "3-0",
          "prob": 6.4,
          "fair": 15.62
        }
      ],
      "over_under": {
        "line": 2.5,
        "over": 50.9,
        "under": 49.1
      },
      "btts": 51.7,
      "model_1x2": {
        "home": 0.57516,
        "draw": 0.2606,
        "away": 0.16424
      },
      "approx_1x2": false,
      "venues": [
        {
          "venue": "virginbet",
          "selection_prices": {
            "home": 1.63,
            "draw": 3.4,
            "away": 5.8
          },
          "implied": {
            "home": 0.6134969325153374,
            "draw": 0.29411764705882354,
            "away": 0.1724137931034483
          },
          "edge_vs_model": {
            "home": -0.06248920000000002,
            "draw": -0.11396000000000006,
            "away": -0.047408000000000006
          }
        },
        {
          "venue": "grosvenor",
          "selection_prices": {
            "home": 1.67,
            "draw": 3.5,
            "away": 5.5
          },
          "implied": {
            "home": 0.5988023952095809,
            "draw": 0.2857142857142857,
            "away": 0.18181818181818182
          },
          "edge_vs_model": {
            "home": -0.03948280000000004,
            "draw": -0.08789999999999998,
            "away": -0.09667999999999999
          }
        },
        {
          "venue": "livescorebet",
          "selection_prices": {
            "home": 1.63,
            "draw": 3.4,
            "away": 5.8
          },
          "implied": {
            "home": 0.6134969325153374,
            "draw": 0.29411764705882354,
            "away": 0.1724137931034483
          },
          "edge_vs_model": {
            "home": -0.06248920000000002,
            "draw": -0.11396000000000006,
            "away": -0.047408000000000006
          }
        },
        {
          "venue": "casumo",
          "selection_prices": {
            "home": 1.65,
            "draw": 3.5,
            "away": 6.0
          },
          "implied": {
            "home": 0.6060606060606061,
            "draw": 0.2857142857142857,
            "away": 0.16666666666666666
          },
          "edge_vs_model": {
            "home": -0.05098600000000009,
            "draw": -0.08789999999999998,
            "away": -0.014560000000000017
          }
        },
        {
          "venue": "leovegas",
          "selection_prices": {
            "home": 1.7,
            "draw": 3.5,
            "away": 5.5
          },
          "implied": {
            "home": 0.5882352941176471,
            "draw": 0.2857142857142857,
            "away": 0.18181818181818182
          },
          "edge_vs_model": {
            "home": -0.022228000000000026,
            "draw": -0.08789999999999998,
            "away": -0.09667999999999999
          }
        },
        {
          "venue": "coral",
          "selection_prices": {
            "home": 1.7,
            "draw": 3.5,
            "away": 5.5
          },
          "implied": {
            "home": 0.5882352941176471,
            "draw": 0.2857142857142857,
            "away": 0.18181818181818182
          },
          "edge_vs_model": {
            "home": -0.022228000000000026,
            "draw": -0.08789999999999998,
            "away": -0.09667999999999999
          }
        },
        {
          "venue": "unibet_uk",
          "selection_prices": {
            "home": 1.7,
            "draw": 3.6,
            "away": 5.5
          },
          "implied": {
            "home": 0.5882352941176471,
            "draw": 0.2777777777777778,
            "away": 0.18181818181818182
          },
          "edge_vs_model": {
            "home": -0.022228000000000026,
            "draw": -0.061840000000000006,
            "away": -0.09667999999999999
          }
        },
        {
          "venue": "smarkets",
          "selection_prices": {
            "home": 1.73,
            "draw": 3.7,
            "away": 6.2
          },
          "implied": {
            "home": 0.5780346820809249,
            "draw": 0.27027027027027023,
            "away": 0.16129032258064516
          },
          "edge_vs_model": {
            "home": -0.004973200000000011,
            "draw": -0.03577999999999992,
            "away": 0.018288000000000082
          }
        },
        {
          "venue": "sport888",
          "selection_prices": {
            "home": 1.67,
            "draw": 3.4,
            "away": 5.0
          },
          "implied": {
            "home": 0.5988023952095809,
            "draw": 0.29411764705882354,
            "away": 0.2
          },
          "edge_vs_model": {
            "home": -0.03948280000000004,
            "draw": -0.11396000000000006,
            "away": -0.17880000000000007
          }
        },
        {
          "venue": "ladbrokes_uk",
          "selection_prices": {
            "home": 1.7,
            "draw": 3.4,
            "away": 5.5
          },
          "implied": {
            "home": 0.5882352941176471,
            "draw": 0.29411764705882354,
            "away": 0.18181818181818182
          },
          "edge_vs_model": {
            "home": -0.022228000000000026,
            "draw": -0.11396000000000006,
            "away": -0.09667999999999999
          }
        },
        {
          "venue": "williamhill",
          "selection_prices": {
            "home": 1.67,
            "draw": 3.4,
            "away": 5.0
          },
          "implied": {
            "home": 0.5988023952095809,
            "draw": 0.29411764705882354,
            "away": 0.2
          },
          "edge_vs_model": {
            "home": -0.03948280000000004,
            "draw": -0.11396000000000006,
            "away": -0.17880000000000007
          }
        },
        {
          "venue": "betfred_uk",
          "selection_prices": {
            "home": 1.73,
            "draw": 3.5,
            "away": 5.5
          },
          "implied": {
            "home": 0.5780346820809249,
            "draw": 0.2857142857142857,
            "away": 0.18181818181818182
          },
          "edge_vs_model": {
            "home": -0.004973200000000011,
            "draw": -0.08789999999999998,
            "away": -0.09667999999999999
          }
        },
        {
          "venue": "paddypower",
          "selection_prices": {
            "home": 1.67,
            "draw": 3.5,
            "away": 5.5
          },
          "implied": {
            "home": 0.5988023952095809,
            "draw": 0.2857142857142857,
            "away": 0.18181818181818182
          },
          "edge_vs_model": {
            "home": -0.03948280000000004,
            "draw": -0.08789999999999998,
            "away": -0.09667999999999999
          }
        },
        {
          "venue": "skybet",
          "selection_prices": {
            "home": 1.67,
            "draw": 3.6,
            "away": 5.5
          },
          "implied": {
            "home": 0.5988023952095809,
            "draw": 0.2777777777777778,
            "away": 0.18181818181818182
          },
          "edge_vs_model": {
            "home": -0.03948280000000004,
            "draw": -0.061840000000000006,
            "away": -0.09667999999999999
          }
        },
        {
          "venue": "matchbook",
          "selection_prices": {
            "home": 1.74,
            "draw": 3.7,
            "away": 6.2
          },
          "implied": {
            "home": 0.5747126436781609,
            "draw": 0.27027027027027023,
            "away": 0.16129032258064516
          },
          "edge_vs_model": {
            "home": 0.0007783999999999569,
            "draw": -0.03577999999999992,
            "away": 0.018288000000000082
          }
        },
        {
          "venue": "betfair_ex_uk",
          "selection_prices": {
            "home": 1.74,
            "draw": 3.7,
            "away": 6.2
          },
          "implied": {
            "home": 0.5747126436781609,
            "draw": 0.27027027027027023,
            "away": 0.16129032258064516
          },
          "edge_vs_model": {
            "home": 0.0007783999999999569,
            "draw": -0.03577999999999992,
            "away": 0.018288000000000082
          }
        },
        {
          "venue": "betvictor",
          "selection_prices": {
            "home": 1.65,
            "draw": 3.6,
            "away": 5.5
          },
          "implied": {
            "home": 0.6060606060606061,
            "draw": 0.2777777777777778,
            "away": 0.18181818181818182
          },
          "edge_vs_model": {
            "home": -0.05098600000000009,
            "draw": -0.061840000000000006,
            "away": -0.09667999999999999
          }
        },
        {
          "venue": "betway",
          "selection_prices": {
            "home": 1.67,
            "draw": 3.5,
            "away": 5.5
          },
          "implied": {
            "home": 0.5988023952095809,
            "draw": 0.2857142857142857,
            "away": 0.18181818181818182
          },
          "edge_vs_model": {
            "home": -0.03948280000000004,
            "draw": -0.08789999999999998,
            "away": -0.09667999999999999
          }
        },
        {
          "venue": "boylesports",
          "selection_prices": {
            "home": 1.67,
            "draw": 3.5,
            "away": 5.0
          },
          "implied": {
            "home": 0.5988023952095809,
            "draw": 0.2857142857142857,
            "away": 0.2
          },
          "edge_vs_model": {
            "home": -0.03948280000000004,
            "draw": -0.08789999999999998,
            "away": -0.17880000000000007
          }
        },
        {
          "venue": "betfair_sb_uk",
          "selection_prices": {
            "home": 1.7,
            "draw": 3.5,
            "away": 5.5
          },
          "implied": {
            "home": 0.5882352941176471,
            "draw": 0.2857142857142857,
            "away": 0.18181818181818182
          },
          "edge_vs_model": {
            "home": -0.022228000000000026,
            "draw": -0.08789999999999998,
            "away": -0.09667999999999999
          }
        }
      ],
      "kickoff": "2026-07-12T01:00:00+00:00"
    },
    {
      "fixture": "France vs Spain",
      "scores": [
        {
          "score": "1-1",
          "prob": 13.3,
          "fair": 7.52
        },
        {
          "score": "2-1",
          "prob": 9.1,
          "fair": 10.99
        },
        {
          "score": "1-0",
          "prob": 8.0,
          "fair": 12.5
        },
        {
          "score": "1-2",
          "prob": 7.0,
          "fair": 14.29
        },
        {
          "score": "2-2",
          "prob": 6.7,
          "fair": 14.93
        },
        {
          "score": "0-0",
          "prob": 6.6,
          "fair": 15.15
        }
      ],
      "over_under": {
        "line": 2.5,
        "over": 54.7,
        "under": 45.3
      },
      "btts": 59.9,
      "model_1x2": {
        "home": 0.412745,
        "draw": 0.284284,
        "away": 0.302971
      },
      "approx_1x2": false,
      "venues": []
    }
  ]
}
