{
  "meta": {
    "generated": "2026-07-07 13:13:58 UTC"
  },
  "fixtures": [
    {
      "fixture": "Argentina vs Egypt",
      "scores": [
        {
          "score": "2-0",
          "prob": 14.8,
          "fair": 6.74,
          "pm_prob": 16.5
        },
        {
          "score": "1-0",
          "prob": 14.5,
          "fair": 6.91,
          "pm_prob": 14.5
        },
        {
          "score": "2-1",
          "prob": 9.8,
          "fair": 10.17,
          "pm_prob": 9.5
        },
        {
          "score": "3-0",
          "prob": 9.8,
          "fair": 10.23,
          "pm_prob": 10.5
        },
        {
          "score": "1-1",
          "prob": 9.0,
          "fair": 11.16,
          "pm_prob": 9.5
        },
        {
          "score": "0-0",
          "prob": 6.9,
          "fair": 14.4,
          "pm_prob": 7.5
        }
      ],
      "over_under": {
        "line": 2.5,
        "over": 50.3,
        "under": 49.7
      },
      "btts": 41.5,
      "model_1x2": {
        "home": 0.722583,
        "draw": 0.191334,
        "away": 0.086082
      },
      "approx_1x2": false,
      "venues": [
        {
          "venue": "casumo",
          "selection_prices": {
            "home": 1.34,
            "draw": 4.75,
            "away": 11.0
          },
          "implied": {
            "home": 0.7462686567164178,
            "draw": 0.21052631578947367,
            "away": 0.09090909090909091
          },
          "edge_vs_model": {
            "home": -0.031738779999999966,
            "draw": -0.09116349999999995,
            "away": -0.05309799999999998
          }
        },
        {
          "venue": "virginbet",
          "selection_prices": {
            "home": 1.32,
            "draw": 4.6,
            "away": 10.5
          },
          "implied": {
            "home": 0.7575757575757576,
            "draw": 0.2173913043478261,
            "away": 0.09523809523809523
          },
          "edge_vs_model": {
            "home": -0.046190439999999944,
            "draw": -0.11986360000000007,
            "away": -0.09613899999999997
          }
        },
        {
          "venue": "livescorebet",
          "selection_prices": {
            "home": 1.32,
            "draw": 4.6,
            "away": 10.5
          },
          "implied": {
            "home": 0.7575757575757576,
            "draw": 0.2173913043478261,
            "away": 0.09523809523809523
          },
          "edge_vs_model": {
            "home": -0.046190439999999944,
            "draw": -0.11986360000000007,
            "away": -0.09613899999999997
          }
        },
        {
          "venue": "grosvenor",
          "selection_prices": {
            "home": 1.34,
            "draw": 4.5,
            "away": 11.0
          },
          "implied": {
            "home": 0.7462686567164178,
            "draw": 0.2222222222222222,
            "away": 0.09090909090909091
          },
          "edge_vs_model": {
            "home": -0.031738779999999966,
            "draw": -0.13899700000000004,
            "away": -0.05309799999999998
          }
        },
        {
          "venue": "ladbrokes_uk",
          "selection_prices": {
            "home": 1.33,
            "draw": 5.0,
            "away": 9.5
          },
          "implied": {
            "home": 0.7518796992481203,
            "draw": 0.2,
            "away": 0.10526315789473684
          },
          "edge_vs_model": {
            "home": -0.038964609999999955,
            "draw": -0.04332999999999998,
            "away": -0.18222099999999997
          }
        },
        {
          "venue": "coral",
          "selection_prices": {
            "home": 1.33,
            "draw": 5.0,
            "away": 9.5
          },
          "implied": {
            "home": 0.7518796992481203,
            "draw": 0.2,
            "away": 0.10526315789473684
          },
          "edge_vs_model": {
            "home": -0.038964609999999955,
            "draw": -0.04332999999999998,
            "away": -0.18222099999999997
          }
        },
        {
          "venue": "betfred_uk",
          "selection_prices": {
            "home": 1.33,
            "draw": 4.6,
            "away": 11.0
          },
          "implied": {
            "home": 0.7518796992481203,
            "draw": 0.2173913043478261,
            "away": 0.09090909090909091
          },
          "edge_vs_model": {
            "home": -0.038964609999999955,
            "draw": -0.11986360000000007,
            "away": -0.05309799999999998
          }
        },
        {
          "venue": "smarkets",
          "selection_prices": {
            "home": 1.37,
            "draw": 5.2,
            "away": 12.5
          },
          "implied": {
            "home": 0.7299270072992701,
            "draw": 0.1923076923076923,
            "away": 0.08
          },
          "edge_vs_model": {
            "home": -0.01006129,
            "draw": -0.005063199999999934,
            "away": 0.07602500000000001
          }
        },
        {
          "venue": "leovegas",
          "selection_prices": {
            "home": 1.33,
            "draw": 4.8,
            "away": 10.5
          },
          "implied": {
            "home": 0.7518796992481203,
            "draw": 0.20833333333333334,
            "away": 0.09523809523809523
          },
          "edge_vs_model": {
            "home": -0.038964609999999955,
            "draw": -0.08159680000000002,
            "away": -0.09613899999999997
          }
        },
        {
          "venue": "betway",
          "selection_prices": {
            "home": 1.3,
            "draw": 4.75,
            "away": 11.0
          },
          "implied": {
            "home": 0.7692307692307692,
            "draw": 0.21052631578947367,
            "away": 0.09090909090909091
          },
          "edge_vs_model": {
            "home": -0.06064210000000003,
            "draw": -0.09116349999999995,
            "away": -0.05309799999999998
          }
        },
        {
          "venue": "unibet_uk",
          "selection_prices": {
            "home": 1.34,
            "draw": 5.0,
            "away": 10.5
          },
          "implied": {
            "home": 0.7462686567164178,
            "draw": 0.2,
            "away": 0.09523809523809523
          },
          "edge_vs_model": {
            "home": -0.031738779999999966,
            "draw": -0.04332999999999998,
            "away": -0.09613899999999997
          }
        },
        {
          "venue": "paddypower",
          "selection_prices": {
            "home": 1.3,
            "draw": 4.75,
            "away": 11.0
          },
          "implied": {
            "home": 0.7692307692307692,
            "draw": 0.21052631578947367,
            "away": 0.09090909090909091
          },
          "edge_vs_model": {
            "home": -0.06064210000000003,
            "draw": -0.09116349999999995,
            "away": -0.05309799999999998
          }
        },
        {
          "venue": "skybet",
          "selection_prices": {
            "home": 1.3,
            "draw": 5.0,
            "away": 11.0
          },
          "implied": {
            "home": 0.7692307692307692,
            "draw": 0.2,
            "away": 0.09090909090909091
          },
          "edge_vs_model": {
            "home": -0.06064210000000003,
            "draw": -0.04332999999999998,
            "away": -0.05309799999999998
          }
        },
        {
          "venue": "betvictor",
          "selection_prices": {
            "home": 1.3,
            "draw": 4.8,
            "away": 11.0
          },
          "implied": {
            "home": 0.7692307692307692,
            "draw": 0.20833333333333334,
            "away": 0.09090909090909091
          },
          "edge_vs_model": {
            "home": -0.06064210000000003,
            "draw": -0.08159680000000002,
            "away": -0.05309799999999998
          }
        },
        {
          "venue": "matchbook",
          "selection_prices": {
            "home": 1.37,
            "draw": 5.0,
            "away": 12.5
          },
          "implied": {
            "home": 0.7299270072992701,
            "draw": 0.2,
            "away": 0.08
          },
          "edge_vs_model": {
            "home": -0.01006129,
            "draw": -0.04332999999999998,
            "away": 0.07602500000000001
          }
        },
        {
          "venue": "sport888",
          "selection_prices": {
            "home": 1.3,
            "draw": 4.5,
            "away": 10.0
          },
          "implied": {
            "home": 0.7692307692307692,
            "draw": 0.2222222222222222,
            "away": 0.1
          },
          "edge_vs_model": {
            "home": -0.06064210000000003,
            "draw": -0.13899700000000004,
            "away": -0.13917999999999997
          }
        },
        {
          "venue": "williamhill",
          "selection_prices": {
            "home": 1.33,
            "draw": 4.6,
            "away": 10.0
          },
          "implied": {
            "home": 0.7518796992481203,
            "draw": 0.2173913043478261,
            "away": 0.1
          },
          "edge_vs_model": {
            "home": -0.038964609999999955,
            "draw": -0.11986360000000007,
            "away": -0.13917999999999997
          }
        },
        {
          "venue": "betfair_ex_uk",
          "selection_prices": {
            "home": 1.37,
            "draw": 5.1,
            "away": 12.5
          },
          "implied": {
            "home": 0.7299270072992701,
            "draw": 0.19607843137254904,
            "away": 0.08
          },
          "edge_vs_model": {
            "home": -0.01006129,
            "draw": -0.024196600000000013,
            "away": 0.07602500000000001
          }
        },
        {
          "venue": "boylesports",
          "selection_prices": {
            "home": 1.29,
            "draw": 4.75,
            "away": 11.0
          },
          "implied": {
            "home": 0.7751937984496123,
            "draw": 0.21052631578947367,
            "away": 0.09090909090909091
          },
          "edge_vs_model": {
            "home": -0.06786793000000002,
            "draw": -0.09116349999999995,
            "away": -0.05309799999999998
          }
        },
        {
          "venue": "polymarket",
          "selection_prices": {
            "home": 1.3605,
            "draw": 5.1282,
            "away": 13.3333
          },
          "implied": {
            "home": 0.735023888276369,
            "draw": 0.19500019500019503,
            "away": 0.07500018750046876
          },
          "edge_vs_model": {
            "home": -0.016925828500000017,
            "draw": -0.018800981200000066,
            "away": 0.14775713060000006
          }
        }
      ],
      "kickoff": "2026-07-07T16:00:00+00:00"
    },
    {
      "fixture": "Switzerland vs Colombia",
      "scores": [
        {
          "score": "1-1",
          "prob": 14.2,
          "fair": 7.06,
          "pm_prob": 15.5
        },
        {
          "score": "0-1",
          "prob": 10.5,
          "fair": 9.54,
          "pm_prob": 12.5
        },
        {
          "score": "0-0",
          "prob": 9.3,
          "fair": 10.7,
          "pm_prob": 10.5
        },
        {
          "score": "1-2",
          "prob": 8.7,
          "fair": 11.55,
          "pm_prob": 9.5
        },
        {
          "score": "0-2",
          "prob": 8.1,
          "fair": 12.34,
          "pm_prob": 8.5
        },
        {
          "score": "1-0",
          "prob": 7.9,
          "fair": 12.73,
          "pm_prob": 9.5
        }
      ],
      "over_under": {
        "line": 2.5,
        "over": 45.5,
        "under": 54.5
      },
      "btts": 51.6,
      "model_1x2": {
        "home": 0.269444,
        "draw": 0.297538,
        "away": 0.433017
      },
      "approx_1x2": false,
      "venues": [
        {
          "venue": "leovegas",
          "selection_prices": {
            "home": 3.6,
            "draw": 3.1,
            "away": 2.25
          },
          "implied": {
            "home": 0.2777777777777778,
            "draw": 0.3225806451612903,
            "away": 0.4444444444444444
          },
          "edge_vs_model": {
            "home": -0.03000159999999996,
            "draw": -0.07763219999999993,
            "away": -0.025711750000000033
          }
        },
        {
          "venue": "casumo",
          "selection_prices": {
            "home": 3.6,
            "draw": 3.05,
            "away": 2.25
          },
          "implied": {
            "home": 0.2777777777777778,
            "draw": 0.3278688524590164,
            "away": 0.4444444444444444
          },
          "edge_vs_model": {
            "home": -0.03000159999999996,
            "draw": -0.09250910000000001,
            "away": -0.025711750000000033
          }
        },
        {
          "venue": "grosvenor",
          "selection_prices": {
            "home": 3.6,
            "draw": 3.0,
            "away": 2.2
          },
          "implied": {
            "home": 0.2777777777777778,
            "draw": 0.3333333333333333,
            "away": 0.45454545454545453
          },
          "edge_vs_model": {
            "home": -0.03000159999999996,
            "draw": -0.10738599999999998,
            "away": -0.04736259999999992
          }
        },
        {
          "venue": "virginbet",
          "selection_prices": {
            "home": 3.5,
            "draw": 3.0,
            "away": 2.2
          },
          "implied": {
            "home": 0.2857142857142857,
            "draw": 0.3333333333333333,
            "away": 0.45454545454545453
          },
          "edge_vs_model": {
            "home": -0.05694599999999994,
            "draw": -0.10738599999999998,
            "away": -0.04736259999999992
          }
        },
        {
          "venue": "livescorebet",
          "selection_prices": {
            "home": 3.5,
            "draw": 3.0,
            "away": 2.2
          },
          "implied": {
            "home": 0.2857142857142857,
            "draw": 0.3333333333333333,
            "away": 0.45454545454545453
          },
          "edge_vs_model": {
            "home": -0.05694599999999994,
            "draw": -0.10738599999999998,
            "away": -0.04736259999999992
          }
        },
        {
          "venue": "unibet_uk",
          "selection_prices": {
            "home": 3.6,
            "draw": 3.1,
            "away": 2.25
          },
          "implied": {
            "home": 0.2777777777777778,
            "draw": 0.3225806451612903,
            "away": 0.4444444444444444
          },
          "edge_vs_model": {
            "home": -0.03000159999999996,
            "draw": -0.07763219999999993,
            "away": -0.025711750000000033
          }
        },
        {
          "venue": "betfred_uk",
          "selection_prices": {
            "home": 3.4,
            "draw": 3.1,
            "away": 2.3
          },
          "implied": {
            "home": 0.29411764705882354,
            "draw": 0.3225806451612903,
            "away": 0.4347826086956522
          },
          "edge_vs_model": {
            "home": -0.08389039999999992,
            "draw": -0.07763219999999993,
            "away": -0.004060900000000145
          }
        },
        {
          "venue": "smarkets",
          "selection_prices": {
            "home": 3.8,
            "draw": 3.15,
            "away": 2.34
          },
          "implied": {
            "home": 0.2631578947368421,
            "draw": 0.31746031746031744,
            "away": 0.4273504273504274
          },
          "edge_vs_model": {
            "home": 0.02388720000000011,
            "draw": -0.06275529999999996,
            "away": 0.013259779999999832
          }
        },
        {
          "venue": "paddypower",
          "selection_prices": {
            "home": 3.6,
            "draw": 3.0,
            "away": 2.2
          },
          "implied": {
            "home": 0.2777777777777778,
            "draw": 0.3333333333333333,
            "away": 0.45454545454545453
          },
          "edge_vs_model": {
            "home": -0.03000159999999996,
            "draw": -0.10738599999999998,
            "away": -0.04736259999999992
          }
        },
        {
          "venue": "skybet",
          "selection_prices": {
            "home": 3.5,
            "draw": 3.0,
            "away": 2.2
          },
          "implied": {
            "home": 0.2857142857142857,
            "draw": 0.3333333333333333,
            "away": 0.45454545454545453
          },
          "edge_vs_model": {
            "home": -0.05694599999999994,
            "draw": -0.10738599999999998,
            "away": -0.04736259999999992
          }
        },
        {
          "venue": "betway",
          "selection_prices": {
            "home": 3.6,
            "draw": 3.0,
            "away": 2.25
          },
          "implied": {
            "home": 0.2777777777777778,
            "draw": 0.3333333333333333,
            "away": 0.4444444444444444
          },
          "edge_vs_model": {
            "home": -0.03000159999999996,
            "draw": -0.10738599999999998,
            "away": -0.025711750000000033
          }
        },
        {
          "venue": "matchbook",
          "selection_prices": {
            "home": 3.85,
            "draw": 3.15,
            "away": 2.34
          },
          "implied": {
            "home": 0.2597402597402597,
            "draw": 0.31746031746031744,
            "away": 0.4273504273504274
          },
          "edge_vs_model": {
            "home": 0.037359400000000154,
            "draw": -0.06275529999999996,
            "away": 0.013259779999999832
          }
        },
        {
          "venue": "betvictor",
          "selection_prices": {
            "home": 3.4,
            "draw": 3.2,
            "away": 2.2
          },
          "implied": {
            "home": 0.29411764705882354,
            "draw": 0.3125,
            "away": 0.45454545454545453
          },
          "edge_vs_model": {
            "home": -0.08389039999999992,
            "draw": -0.04787839999999988,
            "away": -0.04736259999999992
          }
        },
        {
          "venue": "coral",
          "selection_prices": {
            "home": 3.5,
            "draw": 3.1,
            "away": 2.25
          },
          "implied": {
            "home": 0.2857142857142857,
            "draw": 0.3225806451612903,
            "away": 0.4444444444444444
          },
          "edge_vs_model": {
            "home": -0.05694599999999994,
            "draw": -0.07763219999999993,
            "away": -0.025711750000000033
          }
        },
        {
          "venue": "ladbrokes_uk",
          "selection_prices": {
            "home": 3.4,
            "draw": 3.1,
            "away": 2.25
          },
          "implied": {
            "home": 0.29411764705882354,
            "draw": 0.3225806451612903,
            "away": 0.4444444444444444
          },
          "edge_vs_model": {
            "home": -0.08389039999999992,
            "draw": -0.07763219999999993,
            "away": -0.025711750000000033
          }
        },
        {
          "venue": "betfair_ex_uk",
          "selection_prices": {
            "home": 3.85,
            "draw": 3.15,
            "away": 2.34
          },
          "implied": {
            "home": 0.2597402597402597,
            "draw": 0.31746031746031744,
            "away": 0.4273504273504274
          },
          "edge_vs_model": {
            "home": 0.037359400000000154,
            "draw": -0.06275529999999996,
            "away": 0.013259779999999832
          }
        },
        {
          "venue": "sport888",
          "selection_prices": {
            "home": 3.4,
            "draw": 2.9,
            "away": 2.2
          },
          "implied": {
            "home": 0.29411764705882354,
            "draw": 0.3448275862068966,
            "away": 0.45454545454545453
          },
          "edge_vs_model": {
            "home": -0.08389039999999992,
            "draw": -0.13713979999999992,
            "away": -0.04736259999999992
          }
        },
        {
          "venue": "williamhill",
          "selection_prices": {
            "home": 3.5,
            "draw": 2.9,
            "away": 2.2
          },
          "implied": {
            "home": 0.2857142857142857,
            "draw": 0.3448275862068966,
            "away": 0.45454545454545453
          },
          "edge_vs_model": {
            "home": -0.05694599999999994,
            "draw": -0.13713979999999992,
            "away": -0.04736259999999992
          }
        },
        {
          "venue": "boylesports",
          "selection_prices": {
            "home": 3.4,
            "draw": 3.0,
            "away": 2.2
          },
          "implied": {
            "home": 0.29411764705882354,
            "draw": 0.3333333333333333,
            "away": 0.45454545454545453
          },
          "edge_vs_model": {
            "home": -0.08389039999999992,
            "draw": -0.10738599999999998,
            "away": -0.04736259999999992
          }
        },
        {
          "venue": "polymarket",
          "selection_prices": {
            "home": 3.7736,
            "draw": 3.1746,
            "away": 2.3529
          },
          "implied": {
            "home": 0.26499894000423996,
            "draw": 0.315000315000315,
            "away": 0.4250074376301585
          },
          "edge_vs_model": {
            "home": 0.016773878399999997,
            "draw": -0.05543586519999999,
            "away": 0.018845699299999907
          }
        }
      ],
      "kickoff": "2026-07-07T20:00:00+00:00"
    },
    {
      "fixture": "France vs Morocco",
      "scores": [
        {
          "score": "1-0",
          "prob": 17.1,
          "fair": 5.84
        },
        {
          "score": "2-0",
          "prob": 12.5,
          "fair": 7.99
        },
        {
          "score": "1-1",
          "prob": 11.5,
          "fair": 8.67
        },
        {
          "score": "0-0",
          "prob": 10.5,
          "fair": 9.51
        },
        {
          "score": "2-1",
          "prob": 9.8,
          "fair": 10.16
        },
        {
          "score": "0-1",
          "prob": 6.7,
          "fair": 14.93
        }
      ],
      "over_under": {
        "line": 2.5,
        "over": 38.8,
        "under": 61.2
      },
      "btts": 40.7,
      "model_1x2": {
        "home": 0.578238,
        "draw": 0.254602,
        "away": 0.167159
      },
      "approx_1x2": false,
      "venues": []
    },
    {
      "fixture": "Spain vs Belgium",
      "scores": [
        {
          "score": "1-1",
          "prob": 11.2,
          "fair": 8.93
        },
        {
          "score": "2-1",
          "prob": 10.6,
          "fair": 9.41
        },
        {
          "score": "1-0",
          "prob": 9.7,
          "fair": 10.3
        },
        {
          "score": "2-0",
          "prob": 9.5,
          "fair": 10.55
        },
        {
          "score": "3-1",
          "prob": 6.5,
          "fair": 15.38
        },
        {
          "score": "3-0",
          "prob": 5.8,
          "fair": 17.24
        }
      ],
      "over_under": {
        "line": 2.5,
        "over": 57.0,
        "under": 43.0
      },
      "btts": 57.0,
      "model_1x2": {
        "home": 0.579084,
        "draw": 0.238174,
        "away": 0.182743
      },
      "approx_1x2": false,
      "venues": []
    }
  ]
}
