[
  {
    "team": "Mexico",
    "group": "A",
    "P(R32)": 1.0,
    "P(R32)_delta": 0.1092,
    "P(R16)": 1.0,
    "P(R16)_delta": 0.4638,
    "P(QF)": 0.0,
    "P(QF)_delta": -0.2293,
    "P(SF)": 0.0,
    "P(SF)_delta": -0.0828,
    "P(Final)": 0.0,
    "P(Final)_delta": -0.0293,
    "P(win)": 0.0,
    "P(win)_delta": -0.0106,
    "P(group_winner)": 1.0,
    "P(group_winner)_delta": 0.4858
  },
  {
    "team": "South Africa",
    "group": "A",
    "P(R32)": 1.0,
    "P(R32)_delta": 0.5616,
    "P(R16)": 0.0,
    "P(R16)_delta": -0.1464,
    "P(QF)": 0.0,
    "P(QF)_delta": -0.0354,
    "P(SF)": 0.0,
    "P(SF)_delta": -0.0063,
    "P(Final)": 0.0,
    "P(Final)_delta": -0.0013,
    "P(win)": 0.0,
    "P(win)_delta": -0.0001,
    "P(group_winner)": 0.0,
    "P(group_winner)_delta": -0.0883
  },
  {
    "team": "South Korea",
    "group": "A",
    "P(R32)": 0.0,
    "P(R32)_delta": -0.6847,
    "P(R16)": 0.0,
    "P(R16)_delta": -0.3143,
    "P(QF)": 0.0,
    "P(QF)_delta": -0.1085,
    "P(SF)": 0.0,
    "P(SF)_delta": -0.0291,
    "P(Final)": 0.0,
    "P(Final)_delta": -0.0089,
    "P(win)": 0.0,
    "P(win)_delta": -0.0022,
    "P(group_winner)": 0.0,
    "P(group_winner)_delta": -0.1991
  },
  {
    "team": "Czech Republic",
    "group": "A",
    "P(R32)": 0.0,
    "P(R32)_delta": -0.7036,
    "P(R16)": 0.0,
    "P(R16)_delta": -0.336,
    "P(QF)": 0.0,
    "P(QF)_delta": -0.1196,
    "P(SF)": 0.0,
    "P(SF)_delta": -0.0327,
    "P(Final)": 0.0,
    "P(Final)_delta": -0.0094,
    "P(win)": 0.0,
    "P(win)_delta": -0.0017,
    "P(group_winner)": 0.0,
    "P(group_winner)_delta": -0.1983
  },
  {
    "team": "Canada",
    "group": "B",
    "P(R32)": 1.0,
    "P(R32)_delta": 0.2085,
    "P(R16)": 1.0,
    "P(R16)_delta": 0.6693,
    "P(QF)": 0.0,
    "P(QF)_delta": -0.0916,
    "P(SF)": 0.0,
    "P(SF)_delta": -0.0188,
    "P(Final)": 0.0,
    "P(Final)_delta": -0.0043,
    "P(win)": 0.0,
    "P(win)_delta": -0.0011,
    "P(group_winner)": 0.0,
    "P(group_winner)_delta": -0.2602
  },
  {
    "team": "Bosnia and Herzegovina",
    "group": "B",
    "P(R32)": 1.0,
    "P(R32)_delta": 0.3576,
    "P(R16)": 0.0,
    "P(R16)_delta": -0.24,
    "P(QF)": 0.0,
    "P(QF)_delta": -0.0575,
    "P(SF)": 0.0,
    "P(SF)_delta": -0.0099,
    "P(Final)": 0.0,
    "P(Final)_delta": -0.0015,
    "P(win)": 0.0,
    "P(win)_delta": -0.0004,
    "P(group_winner)": 0.0,
    "P(group_winner)_delta": -0.1426
  },
  {
    "team": "Qatar",
    "group": "B",
    "P(R32)": 0.0,
    "P(R32)_delta": -0.3071,
    "P(R16)": 0.0,
    "P(R16)_delta": -0.0659,
    "P(QF)": 0.0,
    "P(QF)_delta": -0.0109,
    "P(SF)": 0.0,
    "P(SF)_delta": -0.0011,
    "P(Final)": 0.0,
    "P(Final)_delta": -0.0002,
    "P(win)": 0.0,
    "P(win)_delta": 0.0,
    "P(group_winner)": 0.0,
    "P(group_winner)_delta": -0.0411
  },
  {
    "team": "Switzerland",
    "group": "B",
    "P(R32)": 1.0,
    "P(R32)_delta": 0.0516,
    "P(R16)": 1.0,
    "P(R16)_delta": 0.3905,
    "P(QF)": 1.0,
    "P(QF)_delta": 0.7117,
    "P(SF)": 0.2787,
    "P(SF)_delta": 0.1614,
    "P(Final)": 0.1048,
    "P(Final)_delta": 0.0558,
    "P(win)": 0.0337,
    "P(win)_delta": 0.0144,
    "P(group_winner)": 1.0,
    "P(group_winner)_delta": 0.4438
  },
  {
    "team": "Brazil",
    "group": "C",
    "P(R32)": 1.0,
    "P(R32)_delta": 0.0141,
    "P(R16)": 1.0,
    "P(R16)_delta": 0.2755,
    "P(QF)": 0.0,
    "P(QF)_delta": -0.5345,
    "P(SF)": 0.0,
    "P(SF)_delta": -0.3478,
    "P(Final)": 0.0,
    "P(Final)_delta": -0.21,
    "P(win)": 0.0,
    "P(win)_delta": -0.123,
    "P(group_winner)": 1.0,
    "P(group_winner)_delta": 0.2844
  },
  {
    "team": "Morocco",
    "group": "C",
    "P(R32)": 1.0,
    "P(R32)_delta": 0.1095,
    "P(R16)": 1.0,
    "P(R16)_delta": 0.5588,
    "P(QF)": 1.0,
    "P(QF)_delta": 0.7528,
    "P(SF)": 0.3071,
    "P(SF)_delta": 0.1965,
    "P(Final)": 0.0999,
    "P(Final)_delta": 0.0538,
    "P(win)": 0.0385,
    "P(win)_delta": 0.021,
    "P(group_winner)": 0.0,
    "P(group_winner)_delta": -0.2145
  },
  {
    "team": "Haiti",
    "group": "C",
    "P(R32)": 0.0,
    "P(R32)_delta": -0.1343,
    "P(R16)": 0.0,
    "P(R16)_delta": -0.0167,
    "P(QF)": 0.0,
    "P(QF)_delta": -0.0015,
    "P(SF)": 0.0,
    "P(SF)_delta": -0.0001,
    "P(Final)": 0.0,
    "P(Final)_delta": 0.0,
    "P(win)": 0.0,
    "P(win)_delta": 0.0,
    "P(group_winner)": 0.0,
    "P(group_winner)_delta": -0.0065
  },
  {
    "team": "Scotland",
    "group": "C",
    "P(R32)": 0.0,
    "P(R32)_delta": -0.6536,
    "P(R16)": 0.0,
    "P(R16)_delta": -0.2189,
    "P(QF)": 0.0,
    "P(QF)_delta": -0.0774,
    "P(SF)": 0.0,
    "P(SF)_delta": -0.022,
    "P(Final)": 0.0,
    "P(Final)_delta": -0.005,
    "P(win)": 0.0,
    "P(win)_delta": -0.0013,
    "P(group_winner)": 0.0,
    "P(group_winner)_delta": -0.0635
  },
  {
    "team": "United States",
    "group": "D",
    "P(R32)": 1.0,
    "P(R32)_delta": 0.2945,
    "P(R16)": 1.0,
    "P(R16)_delta": 0.6668,
    "P(QF)": 0.0,
    "P(QF)_delta": -0.1101,
    "P(SF)": 0.0,
    "P(SF)_delta": -0.0321,
    "P(Final)": 0.0,
    "P(Final)_delta": -0.0088,
    "P(win)": 0.0,
    "P(win)_delta": -0.002,
    "P(group_winner)": 1.0,
    "P(group_winner)_delta": 0.7095
  },
  {
    "team": "Paraguay",
    "group": "D",
    "P(R32)": 1.0,
    "P(R32)_delta": 0.323,
    "P(R16)": 1.0,
    "P(R16)_delta": 0.678,
    "P(QF)": 0.0,
    "P(QF)_delta": -0.1119,
    "P(SF)": 0.0,
    "P(SF)_delta": -0.0336,
    "P(Final)": 0.0,
    "P(Final)_delta": -0.0094,
    "P(win)": 0.0,
    "P(win)_delta": -0.0021,
    "P(group_winner)": 0.0,
    "P(group_winner)_delta": -0.2427
  },
  {
    "team": "Australia",
    "group": "D",
    "P(R32)": 1.0,
    "P(R32)_delta": 0.3417,
    "P(R16)": 0.0,
    "P(R16)_delta": -0.3048,
    "P(QF)": 0.0,
    "P(QF)_delta": -0.1009,
    "P(SF)": 0.0,
    "P(SF)_delta": -0.0305,
    "P(Final)": 0.0,
    "P(Final)_delta": -0.0079,
    "P(win)": 0.0,
    "P(win)_delta": -0.0021,
    "P(group_winner)": 0.0,
    "P(group_winner)_delta": -0.2144
  },
  {
    "team": "Turkey",
    "group": "D",
    "P(R32)": 0.0,
    "P(R32)_delta": -0.7183,
    "P(R16)": 0.0,
    "P(R16)_delta": -0.3654,
    "P(QF)": 0.0,
    "P(QF)_delta": -0.1335,
    "P(SF)": 0.0,
    "P(SF)_delta": -0.0432,
    "P(Final)": 0.0,
    "P(Final)_delta": -0.0126,
    "P(win)": 0.0,
    "P(win)_delta": -0.004,
    "P(group_winner)": 0.0,
    "P(group_winner)_delta": -0.2524
  },
  {
    "team": "Germany",
    "group": "E",
    "P(R32)": 1.0,
    "P(R32)_delta": 0.0201,
    "P(R16)": 0.0,
    "P(R16)_delta": -0.6688,
    "P(QF)": 0.0,
    "P(QF)_delta": -0.3424,
    "P(SF)": 0.0,
    "P(SF)_delta": -0.1923,
    "P(Final)": 0.0,
    "P(Final)_delta": -0.0934,
    "P(win)": 0.0,
    "P(win)_delta": -0.0396,
    "P(group_winner)": 1.0,
    "P(group_winner)_delta": 0.3743
  },
  {
    "team": "Cura\u00e7ao",
    "group": "E",
    "P(R32)": 0.0,
    "P(R32)_delta": -0.079,
    "P(R16)": 0.0,
    "P(R16)_delta": -0.0067,
    "P(QF)": 0.0,
    "P(QF)_delta": -0.0006,
    "P(SF)": 0.0,
    "P(SF)_delta": 0.0,
    "P(Final)": 0.0,
    "P(Final)_delta": 0.0,
    "P(win)": 0.0,
    "P(win)_delta": 0.0,
    "P(group_winner)": 0.0,
    "P(group_winner)_delta": -0.0042
  },
  {
    "team": "Ivory Coast",
    "group": "E",
    "P(R32)": 1.0,
    "P(R32)_delta": 0.194,
    "P(R16)": 0.0,
    "P(R16)_delta": -0.3447,
    "P(QF)": 0.0,
    "P(QF)_delta": -0.1076,
    "P(SF)": 0.0,
    "P(SF)_delta": -0.0352,
    "P(Final)": 0.0,
    "P(Final)_delta": -0.0098,
    "P(win)": 0.0,
    "P(win)_delta": -0.0025,
    "P(group_winner)": 0.0,
    "P(group_winner)_delta": -0.1441
  },
  {
    "team": "Ecuador",
    "group": "E",
    "P(R32)": 1.0,
    "P(R32)_delta": 0.0951,
    "P(R16)": 0.0,
    "P(R16)_delta": -0.468,
    "P(QF)": 0.0,
    "P(QF)_delta": -0.1809,
    "P(SF)": 0.0,
    "P(SF)_delta": -0.0722,
    "P(Final)": 0.0,
    "P(Final)_delta": -0.0266,
    "P(win)": 0.0,
    "P(win)_delta": -0.0086,
    "P(group_winner)": 0.0,
    "P(group_winner)_delta": -0.2261
  },
  {
    "team": "Netherlands",
    "group": "F",
    "P(R32)": 1.0,
    "P(R32)_delta": 0.0686,
    "P(R16)": 0.0,
    "P(R16)_delta": -0.5296,
    "P(QF)": 0.0,
    "P(QF)_delta": -0.3752,
    "P(SF)": 0.0,
    "P(SF)_delta": -0.2029,
    "P(Final)": 0.0,
    "P(Final)_delta": -0.1014,
    "P(win)": 0.0,
    "P(win)_delta": -0.0495,
    "P(group_winner)": 1.0,
    "P(group_winner)_delta": 0.4037
  },
  {
    "team": "Japan",
    "group": "F",
    "P(R32)": 1.0,
    "P(R32)_delta": 0.25,
    "P(R16)": 0.0,
    "P(R16)_delta": -0.2732,
    "P(QF)": 0.0,
    "P(QF)_delta": -0.1335,
    "P(SF)": 0.0,
    "P(SF)_delta": -0.0527,
    "P(Final)": 0.0,
    "P(Final)_delta": -0.0184,
    "P(win)": 0.0,
    "P(win)_delta": -0.0057,
    "P(group_winner)": 0.0,
    "P(group_winner)_delta": -0.2059
  },
  {
    "team": "Sweden",
    "group": "F",
    "P(R32)": 1.0,
    "P(R32)_delta": 0.3327,
    "P(R16)": 0.0,
    "P(R16)_delta": -0.2137,
    "P(QF)": 0.0,
    "P(QF)_delta": -0.0953,
    "P(SF)": 0.0,
    "P(SF)_delta": -0.0352,
    "P(Final)": 0.0,
    "P(Final)_delta": -0.0118,
    "P(win)": 0.0,
    "P(win)_delta": -0.0029,
    "P(group_winner)": 0.0,
    "P(group_winner)_delta": -0.1515
  },
  {
    "team": "Tunisia",
    "group": "F",
    "P(R32)": 0.0,
    "P(R32)_delta": -0.3475,
    "P(R16)": 0.0,
    "P(R16)_delta": -0.0703,
    "P(QF)": 0.0,
    "P(QF)_delta": -0.0202,
    "P(SF)": 0.0,
    "P(SF)_delta": -0.005,
    "P(Final)": 0.0,
    "P(Final)_delta": -0.0009,
    "P(win)": 0.0,
    "P(win)_delta": -0.0001,
    "P(group_winner)": 0.0,
    "P(group_winner)_delta": -0.0462
  },
  {
    "team": "Belgium",
    "group": "G",
    "P(R32)": 1.0,
    "P(R32)_delta": 0.0377,
    "P(R16)": 1.0,
    "P(R16)_delta": 0.3139,
    "P(QF)": 1.0,
    "P(QF)_delta": 0.5714,
    "P(SF)": 0.3083,
    "P(SF)_delta": 0.1154,
    "P(Final)": 0.131,
    "P(Final)_delta": 0.0373,
    "P(win)": 0.0549,
    "P(win)_delta": 0.0127,
    "P(group_winner)": 1.0,
    "P(group_winner)_delta": 0.3525
  },
  {
    "team": "Egypt",
    "group": "G",
    "P(R32)": 1.0,
    "P(R32)_delta": 0.2632,
    "P(R16)": 1.0,
    "P(R16)_delta": 0.6608,
    "P(QF)": 0.0,
    "P(QF)_delta": -0.112,
    "P(SF)": 0.0,
    "P(SF)_delta": -0.0316,
    "P(Final)": 0.0,
    "P(Final)_delta": -0.0086,
    "P(win)": 0.0,
    "P(win)_delta": -0.0019,
    "P(group_winner)": 0.0,
    "P(group_winner)_delta": -0.1557
  },
  {
    "team": "Iran",
    "group": "G",
    "P(R32)": 0.0,
    "P(R32)_delta": -0.7869,
    "P(R16)": 0.0,
    "P(R16)_delta": -0.389,
    "P(QF)": 0.0,
    "P(QF)_delta": -0.1416,
    "P(SF)": 0.0,
    "P(SF)_delta": -0.0444,
    "P(Final)": 0.0,
    "P(Final)_delta": -0.0123,
    "P(win)": 0.0,
    "P(win)_delta": -0.0034,
    "P(group_winner)": 0.0,
    "P(group_winner)_delta": -0.1794
  },
  {
    "team": "New Zealand",
    "group": "G",
    "P(R32)": 0.0,
    "P(R32)_delta": -0.2105,
    "P(R16)": 0.0,
    "P(R16)_delta": -0.0428,
    "P(QF)": 0.0,
    "P(QF)_delta": -0.0053,
    "P(SF)": 0.0,
    "P(SF)_delta": -0.0004,
    "P(Final)": 0.0,
    "P(Final)_delta": 0.0,
    "P(win)": 0.0,
    "P(win)_delta": 0.0,
    "P(group_winner)": 0.0,
    "P(group_winner)_delta": -0.0175
  },
  {
    "team": "Spain",
    "group": "H",
    "P(R32)": 1.0,
    "P(R32)_delta": 0.0107,
    "P(R16)": 1.0,
    "P(R16)_delta": 0.2528,
    "P(QF)": 1.0,
    "P(QF)_delta": 0.4708,
    "P(SF)": 0.6917,
    "P(SF)_delta": 0.2843,
    "P(Final)": 0.4161,
    "P(Final)_delta": 0.1438,
    "P(win)": 0.2519,
    "P(win)_delta": 0.0847,
    "P(group_winner)": 1.0,
    "P(group_winner)_delta": 0.232
  },
  {
    "team": "Cape Verde",
    "group": "H",
    "P(R32)": 1.0,
    "P(R32)_delta": 0.6609,
    "P(R16)": 0.0,
    "P(R16)_delta": -0.068,
    "P(QF)": 0.0,
    "P(QF)_delta": -0.0162,
    "P(SF)": 0.0,
    "P(SF)_delta": -0.0032,
    "P(Final)": 0.0,
    "P(Final)_delta": -0.0003,
    "P(win)": 0.0,
    "P(win)_delta": 0.0,
    "P(group_winner)": 0.0,
    "P(group_winner)_delta": -0.0214
  },
  {
    "team": "Saudi Arabia",
    "group": "H",
    "P(R32)": 0.0,
    "P(R32)_delta": -0.3257,
    "P(R16)": 0.0,
    "P(R16)_delta": -0.0663,
    "P(QF)": 0.0,
    "P(QF)_delta": -0.0161,
    "P(SF)": 0.0,
    "P(SF)_delta": -0.0025,
    "P(Final)": 0.0,
    "P(Final)_delta": -0.0003,
    "P(win)": 0.0,
    "P(win)_delta": -0.0001,
    "P(group_winner)": 0.0,
    "P(group_winner)_delta": -0.0203
  },
  {
    "team": "Uruguay",
    "group": "H",
    "P(R32)": 0.0,
    "P(R32)_delta": -0.8764,
    "P(R16)": 0.0,
    "P(R16)_delta": -0.3802,
    "P(QF)": 0.0,
    "P(QF)_delta": -0.1996,
    "P(SF)": 0.0,
    "P(SF)_delta": -0.0961,
    "P(Final)": 0.0,
    "P(Final)_delta": -0.0403,
    "P(win)": 0.0,
    "P(win)_delta": -0.0133,
    "P(group_winner)": 0.0,
    "P(group_winner)_delta": -0.1904
  },
  {
    "team": "France",
    "group": "I",
    "P(R32)": 1.0,
    "P(R32)_delta": 0.0283,
    "P(R16)": 1.0,
    "P(R16)_delta": 0.2624,
    "P(QF)": 1.0,
    "P(QF)_delta": 0.505,
    "P(SF)": 0.6929,
    "P(SF)_delta": 0.359,
    "P(Final)": 0.3529,
    "P(Final)_delta": 0.1578,
    "P(win)": 0.1915,
    "P(win)_delta": 0.0807,
    "P(group_winner)": 1.0,
    "P(group_winner)_delta": 0.3079
  },
  {
    "team": "Senegal",
    "group": "I",
    "P(R32)": 1.0,
    "P(R32)_delta": 0.3197,
    "P(R16)": 0.0,
    "P(R16)_delta": -0.2816,
    "P(QF)": 0.0,
    "P(QF)_delta": -0.1009,
    "P(SF)": 0.0,
    "P(SF)_delta": -0.0347,
    "P(Final)": 0.0,
    "P(Final)_delta": -0.0107,
    "P(win)": 0.0,
    "P(win)_delta": -0.0027,
    "P(group_winner)": 0.0,
    "P(group_winner)_delta": -0.1174
  },
  {
    "team": "Iraq",
    "group": "I",
    "P(R32)": 0.0,
    "P(R32)_delta": -0.2074,
    "P(R16)": 0.0,
    "P(R16)_delta": -0.0393,
    "P(QF)": 0.0,
    "P(QF)_delta": -0.0066,
    "P(SF)": 0.0,
    "P(SF)_delta": -0.0008,
    "P(Final)": 0.0,
    "P(Final)_delta": -0.0001,
    "P(win)": 0.0,
    "P(win)_delta": 0.0,
    "P(group_winner)": 0.0,
    "P(group_winner)_delta": -0.0164
  },
  {
    "team": "Norway",
    "group": "I",
    "P(R32)": 1.0,
    "P(R32)_delta": 0.1898,
    "P(R16)": 1.0,
    "P(R16)_delta": 0.5957,
    "P(QF)": 1.0,
    "P(QF)_delta": 0.8247,
    "P(SF)": 0.3001,
    "P(SF)_delta": 0.2272,
    "P(Final)": 0.0988,
    "P(Final)_delta": 0.0718,
    "P(win)": 0.0281,
    "P(win)_delta": 0.0179,
    "P(group_winner)": 0.0,
    "P(group_winner)_delta": -0.1741
  },
  {
    "team": "Argentina",
    "group": "J",
    "P(R32)": 1.0,
    "P(R32)_delta": 0.0143,
    "P(R16)": 1.0,
    "P(R16)_delta": 0.3114,
    "P(QF)": 1.0,
    "P(QF)_delta": 0.466,
    "P(SF)": 0.7214,
    "P(SF)_delta": 0.3453,
    "P(Final)": 0.4237,
    "P(Final)_delta": 0.1935,
    "P(win)": 0.2236,
    "P(win)_delta": 0.0888,
    "P(group_winner)": 1.0,
    "P(group_winner)_delta": 0.2226
  },
  {
    "team": "Algeria",
    "group": "J",
    "P(R32)": 1.0,
    "P(R32)_delta": 0.3202,
    "P(R16)": 0.0,
    "P(R16)_delta": -0.2094,
    "P(QF)": 0.0,
    "P(QF)_delta": -0.0746,
    "P(SF)": 0.0,
    "P(SF)_delta": -0.0221,
    "P(Final)": 0.0,
    "P(Final)_delta": -0.0056,
    "P(win)": 0.0,
    "P(win)_delta": -0.0015,
    "P(group_winner)": 0.0,
    "P(group_winner)_delta": -0.0898
  },
  {
    "team": "Austria",
    "group": "J",
    "P(R32)": 1.0,
    "P(R32)_delta": 0.2337,
    "P(R16)": 0.0,
    "P(R16)_delta": -0.2696,
    "P(QF)": 0.0,
    "P(QF)_delta": -0.1138,
    "P(SF)": 0.0,
    "P(SF)_delta": -0.0428,
    "P(Final)": 0.0,
    "P(Final)_delta": -0.0135,
    "P(win)": 0.0,
    "P(win)_delta": -0.0036,
    "P(group_winner)": 0.0,
    "P(group_winner)_delta": -0.1199
  },
  {
    "team": "Jordan",
    "group": "J",
    "P(R32)": 0.0,
    "P(R32)_delta": -0.2081,
    "P(R16)": 0.0,
    "P(R16)_delta": -0.0362,
    "P(QF)": 0.0,
    "P(QF)_delta": -0.0071,
    "P(SF)": 0.0,
    "P(SF)_delta": -0.0009,
    "P(Final)": 0.0,
    "P(Final)_delta": -0.0001,
    "P(win)": 0.0,
    "P(win)_delta": 0.0,
    "P(group_winner)": 0.0,
    "P(group_winner)_delta": -0.0129
  },
  {
    "team": "Portugal",
    "group": "K",
    "P(R32)": 1.0,
    "P(R32)_delta": 0.0403,
    "P(R16)": 1.0,
    "P(R16)_delta": 0.331,
    "P(QF)": 0.0,
    "P(QF)_delta": -0.4175,
    "P(SF)": 0.0,
    "P(SF)_delta": -0.2337,
    "P(Final)": 0.0,
    "P(Final)_delta": -0.1224,
    "P(win)": 0.0,
    "P(win)_delta": -0.0619,
    "P(group_winner)": 0.0,
    "P(group_winner)_delta": -0.5562
  },
  {
    "team": "DR Congo",
    "group": "K",
    "P(R32)": 1.0,
    "P(R32)_delta": 0.6244,
    "P(R16)": 0.0,
    "P(R16)_delta": -0.0931,
    "P(QF)": 0.0,
    "P(QF)_delta": -0.0244,
    "P(SF)": 0.0,
    "P(SF)_delta": -0.0052,
    "P(Final)": 0.0,
    "P(Final)_delta": -0.0008,
    "P(win)": 0.0,
    "P(win)_delta": -0.0001,
    "P(group_winner)": 0.0,
    "P(group_winner)_delta": -0.0386
  },
  {
    "team": "Uzbekistan",
    "group": "K",
    "P(R32)": 0.0,
    "P(R32)_delta": -0.3204,
    "P(R16)": 0.0,
    "P(R16)_delta": -0.071,
    "P(QF)": 0.0,
    "P(QF)_delta": -0.0156,
    "P(SF)": 0.0,
    "P(SF)_delta": -0.0032,
    "P(Final)": 0.0,
    "P(Final)_delta": -0.0003,
    "P(win)": 0.0,
    "P(win)_delta": 0.0,
    "P(group_winner)": 0.0,
    "P(group_winner)_delta": -0.0318
  },
  {
    "team": "Colombia",
    "group": "K",
    "P(R32)": 1.0,
    "P(R32)_delta": 0.0716,
    "P(R16)": 1.0,
    "P(R16)_delta": 0.4,
    "P(QF)": 0.0,
    "P(QF)_delta": -0.3402,
    "P(SF)": 0.0,
    "P(SF)_delta": -0.1844,
    "P(Final)": 0.0,
    "P(Final)_delta": -0.0902,
    "P(win)": 0.0,
    "P(win)_delta": -0.0418,
    "P(group_winner)": 1.0,
    "P(group_winner)_delta": 0.6266
  },
  {
    "team": "England",
    "group": "L",
    "P(R32)": 1.0,
    "P(R32)_delta": 0.025,
    "P(R16)": 1.0,
    "P(R16)_delta": 0.2946,
    "P(QF)": 1.0,
    "P(QF)_delta": 0.5121,
    "P(SF)": 0.6999,
    "P(SF)_delta": 0.405,
    "P(Final)": 0.3726,
    "P(Final)_delta": 0.2011,
    "P(win)": 0.1777,
    "P(win)_delta": 0.0836,
    "P(group_winner)": 1.0,
    "P(group_winner)_delta": 0.3112
  },
  {
    "team": "Croatia",
    "group": "L",
    "P(R32)": 1.0,
    "P(R32)_delta": 0.1169,
    "P(R16)": 0.0,
    "P(R16)_delta": -0.443,
    "P(QF)": 0.0,
    "P(QF)_delta": -0.2069,
    "P(SF)": 0.0,
    "P(SF)_delta": -0.096,
    "P(Final)": 0.0,
    "P(Final)_delta": -0.0374,
    "P(win)": 0.0,
    "P(win)_delta": -0.0135,
    "P(group_winner)": 0.0,
    "P(group_winner)_delta": -0.2514
  },
  {
    "team": "Ghana",
    "group": "L",
    "P(R32)": 1.0,
    "P(R32)_delta": 0.5872,
    "P(R16)": 0.0,
    "P(R16)_delta": -0.0931,
    "P(QF)": 0.0,
    "P(QF)_delta": -0.0246,
    "P(SF)": 0.0,
    "P(SF)_delta": -0.0044,
    "P(Final)": 0.0,
    "P(Final)_delta": -0.0009,
    "P(win)": 0.0,
    "P(win)_delta": -0.0002,
    "P(group_winner)": 0.0,
    "P(group_winner)_delta": -0.0368
  },
  {
    "team": "Panama",
    "group": "L",
    "P(R32)": 0.0,
    "P(R32)_delta": -0.3118,
    "P(R16)": 0.0,
    "P(R16)_delta": -0.0595,
    "P(QF)": 0.0,
    "P(QF)_delta": -0.0131,
    "P(SF)": 0.0,
    "P(SF)_delta": -0.0025,
    "P(Final)": 0.0,
    "P(Final)_delta": -0.0003,
    "P(win)": 0.0,
    "P(win)_delta": 0.0,
    "P(group_winner)": 0.0,
    "P(group_winner)_delta": -0.023
  }
]