[
  {
    "team": "Mexico",
    "group": "A",
    "P(R32)": 1.0,
    "P(R32)_delta": 0.1102,
    "P(R16)": 1.0,
    "P(R16)_delta": 0.4676,
    "P(QF)": 0.0,
    "P(QF)_delta": -0.2303,
    "P(SF)": 0.0,
    "P(SF)_delta": -0.0846,
    "P(Final)": 0.0,
    "P(Final)_delta": -0.0316,
    "P(win)": 0.0,
    "P(win)_delta": -0.0118,
    "P(group_winner)": 1.0,
    "P(group_winner)_delta": 0.4816
  },
  {
    "team": "South Africa",
    "group": "A",
    "P(R32)": 1.0,
    "P(R32)_delta": 0.561,
    "P(R16)": 0.0,
    "P(R16)_delta": -0.1507,
    "P(QF)": 0.0,
    "P(QF)_delta": -0.0359,
    "P(SF)": 0.0,
    "P(SF)_delta": -0.0076,
    "P(Final)": 0.0,
    "P(Final)_delta": -0.0015,
    "P(win)": 0.0,
    "P(win)_delta": -0.0003,
    "P(group_winner)": 0.0,
    "P(group_winner)_delta": -0.0862
  },
  {
    "team": "South Korea",
    "group": "A",
    "P(R32)": 0.0,
    "P(R32)_delta": -0.6918,
    "P(R16)": 0.0,
    "P(R16)_delta": -0.3244,
    "P(QF)": 0.0,
    "P(QF)_delta": -0.1122,
    "P(SF)": 0.0,
    "P(SF)_delta": -0.0312,
    "P(Final)": 0.0,
    "P(Final)_delta": -0.0077,
    "P(win)": 0.0,
    "P(win)_delta": -0.0019,
    "P(group_winner)": 0.0,
    "P(group_winner)_delta": -0.1978
  },
  {
    "team": "Czech Republic",
    "group": "A",
    "P(R32)": 0.0,
    "P(R32)_delta": -0.6994,
    "P(R16)": 0.0,
    "P(R16)_delta": -0.3288,
    "P(QF)": 0.0,
    "P(QF)_delta": -0.1156,
    "P(SF)": 0.0,
    "P(SF)_delta": -0.0314,
    "P(Final)": 0.0,
    "P(Final)_delta": -0.0092,
    "P(win)": 0.0,
    "P(win)_delta": -0.0023,
    "P(group_winner)": 0.0,
    "P(group_winner)_delta": -0.1976
  },
  {
    "team": "Canada",
    "group": "B",
    "P(R32)": 1.0,
    "P(R32)_delta": 0.2101,
    "P(R16)": 1.0,
    "P(R16)_delta": 0.66,
    "P(QF)": 0.0,
    "P(QF)_delta": -0.0957,
    "P(SF)": 0.0,
    "P(SF)_delta": -0.0204,
    "P(Final)": 0.0,
    "P(Final)_delta": -0.0042,
    "P(win)": 0.0,
    "P(win)_delta": -0.0008,
    "P(group_winner)": 0.0,
    "P(group_winner)_delta": -0.2636
  },
  {
    "team": "Bosnia and Herzegovina",
    "group": "B",
    "P(R32)": 1.0,
    "P(R32)_delta": 0.36,
    "P(R16)": 0.0,
    "P(R16)_delta": -0.2286,
    "P(QF)": 0.0,
    "P(QF)_delta": -0.0542,
    "P(SF)": 0.0,
    "P(SF)_delta": -0.008,
    "P(Final)": 0.0,
    "P(Final)_delta": -0.0017,
    "P(win)": 0.0,
    "P(win)_delta": -0.0003,
    "P(group_winner)": 0.0,
    "P(group_winner)_delta": -0.1438
  },
  {
    "team": "Qatar",
    "group": "B",
    "P(R32)": 0.0,
    "P(R32)_delta": -0.3124,
    "P(R16)": 0.0,
    "P(R16)_delta": -0.0651,
    "P(QF)": 0.0,
    "P(QF)_delta": -0.0098,
    "P(SF)": 0.0,
    "P(SF)_delta": -0.0009,
    "P(Final)": 0.0,
    "P(Final)_delta": -0.0001,
    "P(win)": 0.0,
    "P(win)_delta": 0.0,
    "P(group_winner)": 0.0,
    "P(group_winner)_delta": -0.0445
  },
  {
    "team": "Switzerland",
    "group": "B",
    "P(R32)": 1.0,
    "P(R32)_delta": 0.0512,
    "P(R16)": 1.0,
    "P(R16)_delta": 0.3913,
    "P(QF)": 0.4038,
    "P(QF)_delta": 0.1179,
    "P(SF)": 0.1403,
    "P(SF)_delta": 0.0257,
    "P(Final)": 0.0501,
    "P(Final)_delta": 0.0045,
    "P(win)": 0.0157,
    "P(win)_delta": -0.0008,
    "P(group_winner)": 1.0,
    "P(group_winner)_delta": 0.4518
  },
  {
    "team": "Brazil",
    "group": "C",
    "P(R32)": 1.0,
    "P(R32)_delta": 0.0142,
    "P(R16)": 1.0,
    "P(R16)_delta": 0.2716,
    "P(QF)": 0.0,
    "P(QF)_delta": -0.5391,
    "P(SF)": 0.0,
    "P(SF)_delta": -0.355,
    "P(Final)": 0.0,
    "P(Final)_delta": -0.2205,
    "P(win)": 0.0,
    "P(win)_delta": -0.1292,
    "P(group_winner)": 1.0,
    "P(group_winner)_delta": 0.2794
  },
  {
    "team": "Morocco",
    "group": "C",
    "P(R32)": 1.0,
    "P(R32)_delta": 0.108,
    "P(R16)": 1.0,
    "P(R16)_delta": 0.5462,
    "P(QF)": 1.0,
    "P(QF)_delta": 0.7418,
    "P(SF)": 0.3127,
    "P(SF)_delta": 0.196,
    "P(Final)": 0.1038,
    "P(Final)_delta": 0.0555,
    "P(win)": 0.0412,
    "P(win)_delta": 0.0236,
    "P(group_winner)": 0.0,
    "P(group_winner)_delta": -0.2125
  },
  {
    "team": "Haiti",
    "group": "C",
    "P(R32)": 0.0,
    "P(R32)_delta": -0.1427,
    "P(R16)": 0.0,
    "P(R16)_delta": -0.017,
    "P(QF)": 0.0,
    "P(QF)_delta": -0.0021,
    "P(SF)": 0.0,
    "P(SF)_delta": -0.0003,
    "P(Final)": 0.0,
    "P(Final)_delta": 0.0,
    "P(win)": 0.0,
    "P(win)_delta": 0.0,
    "P(group_winner)": 0.0,
    "P(group_winner)_delta": -0.0062
  },
  {
    "team": "Scotland",
    "group": "C",
    "P(R32)": 0.0,
    "P(R32)_delta": -0.6417,
    "P(R16)": 0.0,
    "P(R16)_delta": -0.2147,
    "P(QF)": 0.0,
    "P(QF)_delta": -0.0717,
    "P(SF)": 0.0,
    "P(SF)_delta": -0.0204,
    "P(Final)": 0.0,
    "P(Final)_delta": -0.0043,
    "P(win)": 0.0,
    "P(win)_delta": -0.0009,
    "P(group_winner)": 0.0,
    "P(group_winner)_delta": -0.0607
  },
  {
    "team": "United States",
    "group": "D",
    "P(R32)": 1.0,
    "P(R32)_delta": 0.2919,
    "P(R16)": 1.0,
    "P(R16)_delta": 0.6638,
    "P(QF)": 0.0,
    "P(QF)_delta": -0.1124,
    "P(SF)": 0.0,
    "P(SF)_delta": -0.0323,
    "P(Final)": 0.0,
    "P(Final)_delta": -0.0089,
    "P(win)": 0.0,
    "P(win)_delta": -0.0019,
    "P(group_winner)": 1.0,
    "P(group_winner)_delta": 0.7095
  },
  {
    "team": "Paraguay",
    "group": "D",
    "P(R32)": 1.0,
    "P(R32)_delta": 0.3291,
    "P(R16)": 1.0,
    "P(R16)_delta": 0.6805,
    "P(QF)": 0.0,
    "P(QF)_delta": -0.1082,
    "P(SF)": 0.0,
    "P(SF)_delta": -0.0345,
    "P(Final)": 0.0,
    "P(Final)_delta": -0.0089,
    "P(win)": 0.0,
    "P(win)_delta": -0.0024,
    "P(group_winner)": 0.0,
    "P(group_winner)_delta": -0.2429
  },
  {
    "team": "Australia",
    "group": "D",
    "P(R32)": 1.0,
    "P(R32)_delta": 0.3375,
    "P(R16)": 0.5292,
    "P(R16)_delta": 0.2166,
    "P(QF)": 0.0993,
    "P(QF)_delta": -0.0074,
    "P(SF)": 0.0308,
    "P(SF)_delta": -0.0009,
    "P(Final)": 0.0091,
    "P(Final)_delta": -0.0014,
    "P(win)": 0.0019,
    "P(win)_delta": -0.0009,
    "P(group_winner)": 0.0,
    "P(group_winner)_delta": -0.2195
  },
  {
    "team": "Turkey",
    "group": "D",
    "P(R32)": 0.0,
    "P(R32)_delta": -0.7117,
    "P(R16)": 0.0,
    "P(R16)_delta": -0.3556,
    "P(QF)": 0.0,
    "P(QF)_delta": -0.1325,
    "P(SF)": 0.0,
    "P(SF)_delta": -0.0433,
    "P(Final)": 0.0,
    "P(Final)_delta": -0.0126,
    "P(win)": 0.0,
    "P(win)_delta": -0.0044,
    "P(group_winner)": 0.0,
    "P(group_winner)_delta": -0.247
  },
  {
    "team": "Germany",
    "group": "E",
    "P(R32)": 1.0,
    "P(R32)_delta": 0.0192,
    "P(R16)": 0.0,
    "P(R16)_delta": -0.6697,
    "P(QF)": 0.0,
    "P(QF)_delta": -0.3426,
    "P(SF)": 0.0,
    "P(SF)_delta": -0.1935,
    "P(Final)": 0.0,
    "P(Final)_delta": -0.0932,
    "P(win)": 0.0,
    "P(win)_delta": -0.0406,
    "P(group_winner)": 1.0,
    "P(group_winner)_delta": 0.3772
  },
  {
    "team": "Cura\u00e7ao",
    "group": "E",
    "P(R32)": 0.0,
    "P(R32)_delta": -0.0794,
    "P(R16)": 0.0,
    "P(R16)_delta": -0.0092,
    "P(QF)": 0.0,
    "P(QF)_delta": -0.0008,
    "P(SF)": 0.0,
    "P(SF)_delta": 0.0,
    "P(Final)": 0.0,
    "P(Final)_delta": 0.0,
    "P(win)": 0.0,
    "P(win)_delta": 0.0,
    "P(group_winner)": 0.0,
    "P(group_winner)_delta": -0.0037
  },
  {
    "team": "Ivory Coast",
    "group": "E",
    "P(R32)": 1.0,
    "P(R32)_delta": 0.1893,
    "P(R16)": 0.0,
    "P(R16)_delta": -0.3486,
    "P(QF)": 0.0,
    "P(QF)_delta": -0.1135,
    "P(SF)": 0.0,
    "P(SF)_delta": -0.0362,
    "P(Final)": 0.0,
    "P(Final)_delta": -0.0095,
    "P(win)": 0.0,
    "P(win)_delta": -0.0019,
    "P(group_winner)": 0.0,
    "P(group_winner)_delta": -0.1484
  },
  {
    "team": "Ecuador",
    "group": "E",
    "P(R32)": 1.0,
    "P(R32)_delta": 0.1007,
    "P(R16)": 0.0,
    "P(R16)_delta": -0.4632,
    "P(QF)": 0.0,
    "P(QF)_delta": -0.1787,
    "P(SF)": 0.0,
    "P(SF)_delta": -0.069,
    "P(Final)": 0.0,
    "P(Final)_delta": -0.0248,
    "P(win)": 0.0,
    "P(win)_delta": -0.0077,
    "P(group_winner)": 0.0,
    "P(group_winner)_delta": -0.2251
  },
  {
    "team": "Netherlands",
    "group": "F",
    "P(R32)": 1.0,
    "P(R32)_delta": 0.069,
    "P(R16)": 0.0,
    "P(R16)_delta": -0.5203,
    "P(QF)": 0.0,
    "P(QF)_delta": -0.3666,
    "P(SF)": 0.0,
    "P(SF)_delta": -0.1989,
    "P(Final)": 0.0,
    "P(Final)_delta": -0.0982,
    "P(win)": 0.0,
    "P(win)_delta": -0.0493,
    "P(group_winner)": 1.0,
    "P(group_winner)_delta": 0.4102
  },
  {
    "team": "Japan",
    "group": "F",
    "P(R32)": 1.0,
    "P(R32)_delta": 0.2435,
    "P(R16)": 0.0,
    "P(R16)_delta": -0.2742,
    "P(QF)": 0.0,
    "P(QF)_delta": -0.1383,
    "P(SF)": 0.0,
    "P(SF)_delta": -0.0563,
    "P(Final)": 0.0,
    "P(Final)_delta": -0.0203,
    "P(win)": 0.0,
    "P(win)_delta": -0.0063,
    "P(group_winner)": 0.0,
    "P(group_winner)_delta": -0.2167
  },
  {
    "team": "Sweden",
    "group": "F",
    "P(R32)": 1.0,
    "P(R32)_delta": 0.3364,
    "P(R16)": 0.0,
    "P(R16)_delta": -0.2091,
    "P(QF)": 0.0,
    "P(QF)_delta": -0.091,
    "P(SF)": 0.0,
    "P(SF)_delta": -0.0303,
    "P(Final)": 0.0,
    "P(Final)_delta": -0.0092,
    "P(win)": 0.0,
    "P(win)_delta": -0.0024,
    "P(group_winner)": 0.0,
    "P(group_winner)_delta": -0.1475
  },
  {
    "team": "Tunisia",
    "group": "F",
    "P(R32)": 0.0,
    "P(R32)_delta": -0.345,
    "P(R16)": 0.0,
    "P(R16)_delta": -0.0707,
    "P(QF)": 0.0,
    "P(QF)_delta": -0.0186,
    "P(SF)": 0.0,
    "P(SF)_delta": -0.0052,
    "P(Final)": 0.0,
    "P(Final)_delta": -0.0013,
    "P(win)": 0.0,
    "P(win)_delta": -0.0003,
    "P(group_winner)": 0.0,
    "P(group_winner)_delta": -0.0459
  },
  {
    "team": "Belgium",
    "group": "G",
    "P(R32)": 1.0,
    "P(R32)_delta": 0.0415,
    "P(R16)": 1.0,
    "P(R16)_delta": 0.3127,
    "P(QF)": 1.0,
    "P(QF)_delta": 0.5715,
    "P(SF)": 0.3086,
    "P(SF)_delta": 0.1162,
    "P(Final)": 0.1313,
    "P(Final)_delta": 0.0383,
    "P(win)": 0.0565,
    "P(win)_delta": 0.0163,
    "P(group_winner)": 1.0,
    "P(group_winner)_delta": 0.3617
  },
  {
    "team": "Egypt",
    "group": "G",
    "P(R32)": 1.0,
    "P(R32)_delta": 0.2654,
    "P(R16)": 0.4708,
    "P(R16)_delta": 0.1332,
    "P(QF)": 0.0851,
    "P(QF)_delta": -0.027,
    "P(SF)": 0.0263,
    "P(SF)_delta": -0.0051,
    "P(Final)": 0.0069,
    "P(Final)_delta": -0.0024,
    "P(win)": 0.0015,
    "P(win)_delta": -0.0006,
    "P(group_winner)": 0.0,
    "P(group_winner)_delta": -0.1608
  },
  {
    "team": "Iran",
    "group": "G",
    "P(R32)": 0.0,
    "P(R32)_delta": -0.7831,
    "P(R16)": 0.0,
    "P(R16)_delta": -0.3897,
    "P(QF)": 0.0,
    "P(QF)_delta": -0.1399,
    "P(SF)": 0.0,
    "P(SF)_delta": -0.0449,
    "P(Final)": 0.0,
    "P(Final)_delta": -0.0139,
    "P(win)": 0.0,
    "P(win)_delta": -0.0032,
    "P(group_winner)": 0.0,
    "P(group_winner)_delta": -0.1815
  },
  {
    "team": "New Zealand",
    "group": "G",
    "P(R32)": 0.0,
    "P(R32)_delta": -0.213,
    "P(R16)": 0.0,
    "P(R16)_delta": -0.0457,
    "P(QF)": 0.0,
    "P(QF)_delta": -0.0062,
    "P(SF)": 0.0,
    "P(SF)_delta": -0.0005,
    "P(Final)": 0.0,
    "P(Final)_delta": -0.0001,
    "P(win)": 0.0,
    "P(win)_delta": 0.0,
    "P(group_winner)": 0.0,
    "P(group_winner)_delta": -0.0194
  },
  {
    "team": "Spain",
    "group": "H",
    "P(R32)": 1.0,
    "P(R32)_delta": 0.0121,
    "P(R16)": 1.0,
    "P(R16)_delta": 0.2556,
    "P(QF)": 1.0,
    "P(QF)_delta": 0.4729,
    "P(SF)": 0.6914,
    "P(SF)_delta": 0.2886,
    "P(Final)": 0.4154,
    "P(Final)_delta": 0.1471,
    "P(win)": 0.2554,
    "P(win)_delta": 0.0903,
    "P(group_winner)": 1.0,
    "P(group_winner)_delta": 0.2338
  },
  {
    "team": "Cape Verde",
    "group": "H",
    "P(R32)": 1.0,
    "P(R32)_delta": 0.6532,
    "P(R16)": 0.0,
    "P(R16)_delta": -0.0692,
    "P(QF)": 0.0,
    "P(QF)_delta": -0.015,
    "P(SF)": 0.0,
    "P(SF)_delta": -0.0029,
    "P(Final)": 0.0,
    "P(Final)_delta": -0.0003,
    "P(win)": 0.0,
    "P(win)_delta": 0.0,
    "P(group_winner)": 0.0,
    "P(group_winner)_delta": -0.0223
  },
  {
    "team": "Saudi Arabia",
    "group": "H",
    "P(R32)": 0.0,
    "P(R32)_delta": -0.3317,
    "P(R16)": 0.0,
    "P(R16)_delta": -0.0672,
    "P(QF)": 0.0,
    "P(QF)_delta": -0.0166,
    "P(SF)": 0.0,
    "P(SF)_delta": -0.0027,
    "P(Final)": 0.0,
    "P(Final)_delta": -0.0005,
    "P(win)": 0.0,
    "P(win)_delta": -0.0001,
    "P(group_winner)": 0.0,
    "P(group_winner)_delta": -0.0214
  },
  {
    "team": "Uruguay",
    "group": "H",
    "P(R32)": 0.0,
    "P(R32)_delta": -0.8752,
    "P(R16)": 0.0,
    "P(R16)_delta": -0.3807,
    "P(QF)": 0.0,
    "P(QF)_delta": -0.1996,
    "P(SF)": 0.0,
    "P(SF)_delta": -0.0931,
    "P(Final)": 0.0,
    "P(Final)_delta": -0.0372,
    "P(win)": 0.0,
    "P(win)_delta": -0.0135,
    "P(group_winner)": 0.0,
    "P(group_winner)_delta": -0.1902
  },
  {
    "team": "France",
    "group": "I",
    "P(R32)": 1.0,
    "P(R32)_delta": 0.0297,
    "P(R16)": 1.0,
    "P(R16)_delta": 0.2657,
    "P(QF)": 1.0,
    "P(QF)_delta": 0.5081,
    "P(SF)": 0.6873,
    "P(SF)_delta": 0.3579,
    "P(Final)": 0.3493,
    "P(Final)_delta": 0.1563,
    "P(win)": 0.1915,
    "P(win)_delta": 0.0833,
    "P(group_winner)": 1.0,
    "P(group_winner)_delta": 0.3169
  },
  {
    "team": "Senegal",
    "group": "I",
    "P(R32)": 1.0,
    "P(R32)_delta": 0.318,
    "P(R16)": 0.0,
    "P(R16)_delta": -0.2796,
    "P(QF)": 0.0,
    "P(QF)_delta": -0.0999,
    "P(SF)": 0.0,
    "P(SF)_delta": -0.0364,
    "P(Final)": 0.0,
    "P(Final)_delta": -0.0114,
    "P(win)": 0.0,
    "P(win)_delta": -0.0032,
    "P(group_winner)": 0.0,
    "P(group_winner)_delta": -0.1188
  },
  {
    "team": "Iraq",
    "group": "I",
    "P(R32)": 0.0,
    "P(R32)_delta": -0.2122,
    "P(R16)": 0.0,
    "P(R16)_delta": -0.0396,
    "P(QF)": 0.0,
    "P(QF)_delta": -0.0071,
    "P(SF)": 0.0,
    "P(SF)_delta": -0.0011,
    "P(Final)": 0.0,
    "P(Final)_delta": -0.0001,
    "P(win)": 0.0,
    "P(win)_delta": -0.0001,
    "P(group_winner)": 0.0,
    "P(group_winner)_delta": -0.0182
  },
  {
    "team": "Norway",
    "group": "I",
    "P(R32)": 1.0,
    "P(R32)_delta": 0.1958,
    "P(R16)": 1.0,
    "P(R16)_delta": 0.5961,
    "P(QF)": 1.0,
    "P(QF)_delta": 0.8253,
    "P(SF)": 0.3008,
    "P(SF)_delta": 0.2285,
    "P(Final)": 0.1043,
    "P(Final)_delta": 0.0775,
    "P(win)": 0.029,
    "P(win)_delta": 0.0186,
    "P(group_winner)": 0.0,
    "P(group_winner)_delta": -0.1799
  },
  {
    "team": "Argentina",
    "group": "J",
    "P(R32)": 1.0,
    "P(R32)_delta": 0.0144,
    "P(R16)": 1.0,
    "P(R16)_delta": 0.308,
    "P(QF)": 0.8156,
    "P(QF)_delta": 0.278,
    "P(SF)": 0.5514,
    "P(SF)_delta": 0.1702,
    "P(Final)": 0.3251,
    "P(Final)_delta": 0.0917,
    "P(win)": 0.1741,
    "P(win)_delta": 0.0377,
    "P(group_winner)": 1.0,
    "P(group_winner)_delta": 0.2225
  },
  {
    "team": "Algeria",
    "group": "J",
    "P(R32)": 1.0,
    "P(R32)_delta": 0.3176,
    "P(R16)": 0.0,
    "P(R16)_delta": -0.2114,
    "P(QF)": 0.0,
    "P(QF)_delta": -0.0783,
    "P(SF)": 0.0,
    "P(SF)_delta": -0.0255,
    "P(Final)": 0.0,
    "P(Final)_delta": -0.007,
    "P(win)": 0.0,
    "P(win)_delta": -0.0018,
    "P(group_winner)": 0.0,
    "P(group_winner)_delta": -0.0921
  },
  {
    "team": "Austria",
    "group": "J",
    "P(R32)": 1.0,
    "P(R32)_delta": 0.241,
    "P(R16)": 0.0,
    "P(R16)_delta": -0.2683,
    "P(QF)": 0.0,
    "P(QF)_delta": -0.1117,
    "P(SF)": 0.0,
    "P(SF)_delta": -0.0415,
    "P(Final)": 0.0,
    "P(Final)_delta": -0.0123,
    "P(win)": 0.0,
    "P(win)_delta": -0.0031,
    "P(group_winner)": 0.0,
    "P(group_winner)_delta": -0.1169
  },
  {
    "team": "Jordan",
    "group": "J",
    "P(R32)": 0.0,
    "P(R32)_delta": -0.2154,
    "P(R16)": 0.0,
    "P(R16)_delta": -0.0386,
    "P(QF)": 0.0,
    "P(QF)_delta": -0.0065,
    "P(SF)": 0.0,
    "P(SF)_delta": -0.0008,
    "P(Final)": 0.0,
    "P(Final)_delta": -0.0001,
    "P(win)": 0.0,
    "P(win)_delta": 0.0,
    "P(group_winner)": 0.0,
    "P(group_winner)_delta": -0.0135
  },
  {
    "team": "Portugal",
    "group": "K",
    "P(R32)": 1.0,
    "P(R32)_delta": 0.0444,
    "P(R16)": 1.0,
    "P(R16)_delta": 0.3372,
    "P(QF)": 0.0,
    "P(QF)_delta": -0.4135,
    "P(SF)": 0.0,
    "P(SF)_delta": -0.2271,
    "P(Final)": 0.0,
    "P(Final)_delta": -0.1163,
    "P(win)": 0.0,
    "P(win)_delta": -0.0583,
    "P(group_winner)": 0.0,
    "P(group_winner)_delta": -0.5506
  },
  {
    "team": "DR Congo",
    "group": "K",
    "P(R32)": 1.0,
    "P(R32)_delta": 0.6219,
    "P(R16)": 0.0,
    "P(R16)_delta": -0.0926,
    "P(QF)": 0.0,
    "P(QF)_delta": -0.0223,
    "P(SF)": 0.0,
    "P(SF)_delta": -0.0054,
    "P(Final)": 0.0,
    "P(Final)_delta": -0.0009,
    "P(win)": 0.0,
    "P(win)_delta": -0.0001,
    "P(group_winner)": 0.0,
    "P(group_winner)_delta": -0.0427
  },
  {
    "team": "Uzbekistan",
    "group": "K",
    "P(R32)": 0.0,
    "P(R32)_delta": -0.3226,
    "P(R16)": 0.0,
    "P(R16)_delta": -0.0743,
    "P(QF)": 0.0,
    "P(QF)_delta": -0.0152,
    "P(SF)": 0.0,
    "P(SF)_delta": -0.0032,
    "P(Final)": 0.0,
    "P(Final)_delta": -0.0004,
    "P(win)": 0.0,
    "P(win)_delta": -0.0001,
    "P(group_winner)": 0.0,
    "P(group_winner)_delta": -0.0325
  },
  {
    "team": "Colombia",
    "group": "K",
    "P(R32)": 1.0,
    "P(R32)_delta": 0.0708,
    "P(R16)": 1.0,
    "P(R16)_delta": 0.3998,
    "P(QF)": 0.5962,
    "P(QF)_delta": 0.2473,
    "P(SF)": 0.2512,
    "P(SF)_delta": 0.0579,
    "P(Final)": 0.1183,
    "P(Final)_delta": 0.0238,
    "P(win)": 0.0481,
    "P(win)_delta": 0.0022,
    "P(group_winner)": 1.0,
    "P(group_winner)_delta": 0.6258
  },
  {
    "team": "England",
    "group": "L",
    "P(R32)": 1.0,
    "P(R32)_delta": 0.0272,
    "P(R16)": 1.0,
    "P(R16)_delta": 0.2995,
    "P(QF)": 1.0,
    "P(QF)_delta": 0.5179,
    "P(SF)": 0.6992,
    "P(SF)_delta": 0.4107,
    "P(Final)": 0.3861,
    "P(Final)_delta": 0.216,
    "P(win)": 0.1853,
    "P(win)_delta": 0.0926,
    "P(group_winner)": 1.0,
    "P(group_winner)_delta": 0.3077
  },
  {
    "team": "Croatia",
    "group": "L",
    "P(R32)": 1.0,
    "P(R32)_delta": 0.1179,
    "P(R16)": 0.0,
    "P(R16)_delta": -0.445,
    "P(QF)": 0.0,
    "P(QF)_delta": -0.2085,
    "P(SF)": 0.0,
    "P(SF)_delta": -0.0942,
    "P(Final)": 0.0,
    "P(Final)_delta": -0.0379,
    "P(win)": 0.0,
    "P(win)_delta": -0.0137,
    "P(group_winner)": 0.0,
    "P(group_winner)_delta": -0.2464
  },
  {
    "team": "Ghana",
    "group": "L",
    "P(R32)": 1.0,
    "P(R32)_delta": 0.5868,
    "P(R16)": 0.0,
    "P(R16)_delta": -0.0969,
    "P(QF)": 0.0,
    "P(QF)_delta": -0.0245,
    "P(SF)": 0.0,
    "P(SF)_delta": -0.0047,
    "P(Final)": 0.0,
    "P(Final)_delta": -0.0006,
    "P(win)": 0.0,
    "P(win)_delta": -0.0001,
    "P(group_winner)": 0.0,
    "P(group_winner)_delta": -0.039
  },
  {
    "team": "Panama",
    "group": "L",
    "P(R32)": 0.0,
    "P(R32)_delta": -0.3118,
    "P(R16)": 0.0,
    "P(R16)_delta": -0.0568,
    "P(QF)": 0.0,
    "P(QF)_delta": -0.0118,
    "P(SF)": 0.0,
    "P(SF)_delta": -0.002,
    "P(Final)": 0.0,
    "P(Final)_delta": -0.0002,
    "P(win)": 0.0,
    "P(win)_delta": 0.0,
    "P(group_winner)": 0.0,
    "P(group_winner)_delta": -0.0223
  }
]