{
  "fixtures": [
    {
      "dc": {
        "away": 0.119513,
        "draw": 0.189867,
        "home": 0.69062
      },
      "elo": {
        "away": 0.203928,
        "draw": 0.257735,
        "home": 0.538336
      },
      "fixture": "Brazil vs Norway",
      "gb_lambda_away": 1.186382,
      "gb_lambda_home": 2.321156,
      "generated": "2026-07-04T22:15:52",
      "kickoff": "2026-07-05 20:00:00+00:00",
      "lambda_away": 0.835879,
      "lambda_home": 2.25617,
      "market": {
        "away": 0.212725,
        "draw": 0.256993,
        "home": 0.530283
      },
      "match_id": "a4634eae056c18d705e3feffb347163f",
      "model": {
        "away": 0.183881,
        "draw": 0.23693,
        "home": 0.579189
      }
    },
    {
      "dc": {
        "away": 0.496668,
        "draw": 0.254695,
        "home": 0.248637
      },
      "elo": {
        "away": 0.292908,
        "draw": 0.288115,
        "home": 0.418977
      },
      "fixture": "Mexico vs England",
      "gb_lambda_away": 1.076123,
      "gb_lambda_home": 1.142956,
      "generated": "2026-07-04T22:15:52",
      "kickoff": "2026-07-06 00:00:00+00:00",
      "lambda_away": 1.668738,
      "lambda_home": 1.116324,
      "market": {
        "away": 0.393915,
        "draw": 0.301264,
        "home": 0.304821
      },
      "match_id": "e61a7b471cadc8e3849158ed59d49cab",
      "model": {
        "away": 0.41464,
        "draw": 0.285978,
        "home": 0.299381
      }
    },
    {
      "dc": {
        "away": 0.455018,
        "draw": 0.266642,
        "home": 0.278339
      },
      "elo": {
        "away": 0.505811,
        "draw": 0.268274,
        "home": 0.225916
      },
      "fixture": "Portugal vs Spain",
      "gb_lambda_away": 1.351417,
      "gb_lambda_home": 1.042037,
      "generated": "2026-07-04T22:15:52",
      "kickoff": "2026-07-06 19:00:00+00:00",
      "lambda_away": 1.528925,
      "lambda_home": 1.144851,
      "market": {
        "away": 0.501991,
        "draw": 0.262369,
        "home": 0.23564
      },
      "match_id": "16ed3adcf661b3a9bea39871a2d204df",
      "model": {
        "away": 0.488281,
        "draw": 0.264241,
        "home": 0.247477
      }
    },
    {
      "dc": {
        "away": 0.499549,
        "draw": 0.230186,
        "home": 0.270265
      },
      "elo": {
        "away": 0.334461,
        "draw": 0.292733,
        "home": 0.372806
      },
      "fixture": "United States vs Belgium",
      "gb_lambda_away": 2.198289,
      "gb_lambda_home": 1.60947,
      "generated": "2026-07-04T22:15:52",
      "kickoff": "2026-07-07 00:00:00+00:00",
      "lambda_away": 1.945425,
      "lambda_home": 1.392313,
      "market": {
        "away": 0.366238,
        "draw": 0.283742,
        "home": 0.35002
      },
      "match_id": "810f80b3ae79f5e86b3747ca15718ed8",
      "model": {
        "away": 0.403054,
        "draw": 0.268575,
        "home": 0.328372
      }
    },
    {
      "dc": {
        "away": 0.108396,
        "draw": 0.209373,
        "home": 0.68223
      },
      "elo": {
        "away": 0.076243,
        "draw": 0.140246,
        "home": 0.783511
      },
      "fixture": "Argentina vs Egypt",
      "gb_lambda_away": 0.554108,
      "gb_lambda_home": 1.722615,
      "generated": "2026-07-04T22:15:52",
      "kickoff": "2026-07-07 16:00:00+00:00",
      "lambda_away": 0.653488,
      "lambda_home": 1.978442,
      "market": {
        "away": 0.09283,
        "draw": 0.19859,
        "home": 0.708581
      },
      "match_id": "190922affd0be754bfefd71548dbf90d",
      "model": {
        "away": 0.095841,
        "draw": 0.19599,
        "home": 0.708169
      }
    },
    {
      "dc": {
        "away": 0.46154,
        "draw": 0.274814,
        "home": 0.263647
      },
      "elo": {
        "away": 0.406757,
        "draw": 0.289785,
        "home": 0.303458
      },
      "fixture": "Switzerland vs Colombia",
      "gb_lambda_away": 1.363682,
      "gb_lambda_home": 1.150129,
      "generated": "2026-07-04T22:15:52",
      "kickoff": "2026-07-07 20:00:00+00:00",
      "lambda_away": 1.467753,
      "lambda_home": 1.048224,
      "market": {
        "away": 0.427617,
        "draw": 0.308452,
        "home": 0.263931
      },
      "match_id": "a6da973c5749ce60adab77d64b3664f4",
      "model": {
        "away": 0.435708,
        "draw": 0.296494,
        "home": 0.267798
      }
    }
  ],
  "meta": {
    "generated": "2026-07-04T22:15:52"
  }
}
