{
  "fixtures": [
    {
      "dc": {
        "away": 0.39131,
        "draw": 0.290425,
        "home": 0.318265
      },
      "disagree3pp": {
        "away": true,
        "draw": true,
        "home": true
      },
      "elo": {
        "away": 0.425797,
        "draw": 0.287017,
        "home": 0.287186
      },
      "fixture": "England vs Argentina",
      "gb_lambda_away": 1.367299,
      "gb_lambda_home": 1.074836,
      "generated": "2026-07-15T20:48:51",
      "kickoff": "2026-07-15 19:00:00+00:00",
      "lambda_away": 1.256432,
      "lambda_home": 1.106702,
      "market": {
        "away": 0.850794,
        "draw": 0.140873,
        "home": 0.008333
      },
      "match_id": "ced22494ae0bbb8cc4f7108bf6f493df",
      "model": {
        "away": 0.796535,
        "draw": 0.163096,
        "home": 0.040369
      },
      "model_raw": {
        "away": 0.670449,
        "draw": 0.200353,
        "home": 0.129198
      },
      "mw90": {
        "away": 0.805708,
        "draw": 0.155743,
        "home": 0.038549
      },
      "shrink": {
        "away": 0.796534,
        "draw": 0.163096,
        "home": 0.040369
      },
      "tl_lambda_blend_away": 1.098921,
      "tl_lambda_blend_home": 0.967961,
      "tl_lambda_market_total": 1.800255,
      "tl_n_market_quotes": 10,
      "tl_weight_market": 0.526316
    }
  ],
  "meta": {
    "generated": "2026-07-15T20:48:51"
  }
}
